[{"kind": "Listing", "data": {"modhash": "", "children": [{"kind": "t3", "data": {"contest_mode": false, "banned_by": null, "media_embed": {}, "subreddit": "guns", "selftext_html": null, "selftext": "", "likes": null, "suggested_sort": null, "user_reports": [], "secure_media": null, "link_flair_text": null, "id": "65lkfr", "gilded": 0, "secure_media_embed": {}, "clicked": false, "score": 725, "report_reasons": null, "author": "fat_italian_stallion", "saved": false, "mod_reports": [], "name": "t3_65lkfr", "subreddit_name_prefixed": "r/guns", "approved_by": null, "over_18": false, "domain": "i.imgur.com", "hidden": false, "preview": {"images": [{"source": {"url": "https://i.redditmedia.com/G8_svJizy-EMgjcSZcnU55YX4CQY1CGFYMwrJCPsDpk.jpg?s=2f06202b1252192d7a1ca57db5e8a15b", "width": 4032, "height": 3024}, "resolutions": [{"url": "https://i.redditmedia.com/G8_svJizy-EMgjcSZcnU55YX4CQY1CGFYMwrJCPsDpk.jpg?fit=crop&amp;crop=faces%2Centropy&amp;arh=2&amp;w=108&amp;s=3df3219259ec01b5e4e7b2691952eedf", "width": 108, "height": 81}, {"url": "https://i.redditmedia.com/G8_svJizy-EMgjcSZcnU55YX4CQY1CGFYMwrJCPsDpk.jpg?fit=crop&amp;crop=faces%2Centropy&amp;arh=2&amp;w=216&amp;s=9d7b0474d393079f6f7bef1e01ec8628", "width": 216, "height": 162}, {"url": "https://i.redditmedia.com/G8_svJizy-EMgjcSZcnU55YX4CQY1CGFYMwrJCPsDpk.jpg?fit=crop&amp;crop=faces%2Centropy&amp;arh=2&amp;w=320&amp;s=9987e49fd42575336498fa4b34949fa9", "width": 320, "height": 240}, {"url": "https://i.redditmedia.com/G8_svJizy-EMgjcSZcnU55YX4CQY1CGFYMwrJCPsDpk.jpg?fit=crop&amp;crop=faces%2Centropy&amp;arh=2&amp;w=640&amp;s=8d382c8414e4b4f27fa669294355bff0", "width": 640, "height": 480}, {"url": "https://i.redditmedia.com/G8_svJizy-EMgjcSZcnU55YX4CQY1CGFYMwrJCPsDpk.jpg?fit=crop&amp;crop=faces%2Centropy&amp;arh=2&amp;w=960&amp;s=b27d4645a5014e56f971366ddce3380e", "width": 960, "height": 720}, {"url": "https://i.redditmedia.com/G8_svJizy-EMgjcSZcnU55YX4CQY1CGFYMwrJCPsDpk.jpg?fit=crop&amp;crop=faces%2Centropy&amp;arh=2&amp;w=1080&amp;s=75c39d502d2df58475a1afa0bafb52ec", "width": 1080, "height": 810}], "variants": {}, "id": "xUhxbzPkI0N9eczn-F81XZvFm3Pq-iO6we08E6Sr5O8"}], "enabled": true}, "thumbnail": "https://b.thumbs.redditmedia.com/y-8RKoaLIEeE1zD1ce1R_iyhKKMV9uY9bZJ7WtaeuOM.jpg", "subreddit_id": "t5_2qhc8", "edited": false, "link_flair_css_class": null, "author_flair_css_class": "up", "downs": 0, "brand_safe": false, "archived": false, "removal_reason": null, "post_hint": "image", "is_self": false, "hide_score": false, "spoiler": false, "permalink": "/r/guns/comments/65lkfr/some_kind_of_saturday_alliteration/", "num_reports": null, "locked": false, "stickied": false, "created": 1492320761.0, "url": "http://i.imgur.com/UsvkJ33.jpg", "author_flair_text": "6 | Know-it-all", "quarantine": false, "title": "Some Kind of Saturday Alliteration", "created_utc": 1492291961.0, "distinguished": null, "media": null, "upvote_ratio": 0.96, "num_comments": 68, "visited": false, "subreddit_type": "public", "ups": 725}}], "after": null, "before": null}}, {"kind": "Listing", "data": {"modhash": "", "children": [{"kind": "t1", "data": {"subreddit_id": "t5_2qhc8", "removal_reason": null, "link_id": "t3_65lkfr", "likes": null, "replies": "", "user_reports": [], "id": "dgb8zfs", "gilded": 0, "archived": false, "score": 87, "report_reasons": null, "author": "Johncameron2015", "parent_id": "t3_65lkfr", "subreddit_name_prefixed": "r/guns", "controversiality": 0, "body": "i dont know if i like the guns or the idea of a kitchen safe more", "edited": false, "downs": 0, "body_html": "&lt;div class=\"md\"&gt;&lt;p&gt;i dont know if i like the guns or the idea of a kitchen safe more&lt;/p&gt;\n&lt;/div&gt;", "subreddit": "guns", "name": "t1_dgb8zfs", "score_hidden": false, "stickied": false, "created": 1492322846.0, "created_utc": 1492294046.0, "depth": 0, "mod_reports": [], "subreddit_type": "public", "ups": 87}}, {"kind": "t1", "data": {"subreddit_id": "t5_2qhc8", "removal_reason": null, "link_id": "t3_65lkfr", "likes": null, "replies": {"kind": "Listing", "data": {"modhash": "", "children": [{"kind": "t1", "data": {"subreddit_id": "t5_2qhc8", "removal_reason": null, "link_id": "t3_65lkfr", "likes": null, "replies": {"kind": "Listing", "data": {"modhash": "", "children": [{"kind": "t1", "data": {"subreddit_id": "t5_2qhc8", "removal_reason": null, "link_id": "t3_65lkfr", "likes": null, "replies": {"kind": "Listing", "data": {"modhash": "", "children": [{"kind": "t1", "data": {"subreddit_id": "t5_2qhc8", "removal_reason": null, "link_id": "t3_65lkfr", "likes": null, "replies": {"kind": "Listing", "data": {"modhash": "", "children": [{"kind": "t1", "data": {"subreddit_id": "t5_2qhc8", "removal_reason": null, "link_id": "t3_65lkfr", "likes": null, "replies": {"kind": "Listing", "data": {"modhash": "", "children": [{"kind": "t1", "data": {"subreddit_id": "t5_2qhc8", "removal_reason": null, "link_id": "t3_65lkfr", "likes": null, "replies": "", "user_reports": [], "id": "dgbngv6", "gilded": 0, "archived": false, "score": 6, "report_reasons": null, "author": "fat_italian_stallion", "parent_id": "t1_dgbmy7k", "subreddit_name_prefixed": "r/guns", "controversiality": 0, "body": "At the brick and mortar", "edited": false, "downs": 0, "body_html": "&lt;div class=\"md\"&gt;&lt;p&gt;At the brick and mortar&lt;/p&gt;\n&lt;/div&gt;", "subreddit": "guns", "name": "t1_dgbngv6", "score_hidden": false, "stickied": false, "created": 1492343976.0, "created_utc": 1492315176.0, "depth": 5, "mod_reports": [], "subreddit_type": "public", "ups": 6}}], "after": null, "before": null}}, "user_reports": [], "id": "dgbmy7k", "gilded": 0, "archived": false, "score": 1, "report_reasons": null, "author": "snakies", "parent_id": "t1_dgbmlp1", "subreddit_name_prefixed": "r/guns", "controversiality": 0, "body": "Not to argue but ALL fs2000 on buds are out of stock and cheapest on gunbroker that is gen1 trigger is $2800", "edited": false, "downs": 0, "body_html": "&lt;div class=\"md\"&gt;&lt;p&gt;Not to argue but ALL fs2000 on buds are out of stock and cheapest on gunbroker that is gen1 trigger is $2800&lt;/p&gt;\n&lt;/div&gt;", "subreddit": "guns", "name": "t1_dgbmy7k", "score_hidden": false, "stickied": false, "created": 1492343134.0, "created_utc": 1492314334.0, "depth": 4, "mod_reports": [], "subreddit_type": "public", "ups": 1}}], "after": null, "before": null}}, "user_reports": [], "id": "dgbmlp1", "gilded": 0, "archived": false, "score": 7, "report_reasons": null, "author": "fat_italian_stallion", "parent_id": "t1_dgblmyh", "subreddit_name_prefixed": "r/guns", "controversiality": 0, "body": "Yeah, screw that. Gunbroker easy find for $1800. Buds has gen 1 with integrated optic for 2200", "edited": false, "downs": 0, "body_html": "&lt;div class=\"md\"&gt;&lt;p&gt;Yeah, screw that. Gunbroker easy find for $1800. Buds has gen 1 with integrated optic for 2200&lt;/p&gt;\n&lt;/div&gt;", "subreddit": "guns", "name": "t1_dgbmlp1", "score_hidden": false, "stickied": false, "created": 1492342613.0, "created_utc": 1492313813.0, "depth": 3, "mod_reports": [], "subreddit_type": "public", "ups": 7}}], "after": null, "before": null}}, "user_reports": [], "id": "dgblmyh", "gilded": 0, "archived": false, "score": 2, "report_reasons": null, "author": "snakies", "parent_id": "t1_dgbbh3y", "subreddit_name_prefixed": "r/guns", "controversiality": 0, "body": "Looks like you need one of these still.\nhttps://www.reddit.com/r/Gunsforsale/comments/650i11/wts_fn_fs2000_odgreen_az_gen1_trigger_0065xx/?st=J1K463TP&amp;sh=e681962f", "edited": false, "downs": 0, "body_html": "&lt;div class=\"md\"&gt;&lt;p&gt;Looks like you need one of these still.\n&lt;a href=\"https://www.reddit.com/r/Gunsforsale/comments/650i11/wts_fn_fs2000_odgreen_az_gen1_trigger_0065xx/?st=J1K463TP&amp;amp;sh=e681962f\"&gt;https://www.reddit.com/r/Gunsforsale/comments/650i11/wts_fn_fs2000_odgreen_az_gen1_trigger_0065xx/?st=J1K463TP&amp;amp;sh=e681962f&lt;/a&gt;&lt;/p&gt;\n&lt;/div&gt;", "subreddit": "guns", "name": "t1_dgblmyh", "score_hidden": false, "stickied": false, "created": 1492341125.0, "created_utc": 1492312325.0, "depth": 2, "mod_reports": [], "subreddit_type": "public", "ups": 2}}], "after": null, "before": null}}, "user_reports": [], "id": "dgbbh3y", "gilded": 0, "archived": false, "score": 46, "report_reasons": null, "author": "fat_italian_stallion", "parent_id": "t1_dgbbfkz", "subreddit_name_prefixed": "r/guns", "controversiality": 0, "body": "The others are the problem, ps90 still waiting on stamp", "edited": false, "downs": 0, "body_html": "&lt;div class=\"md\"&gt;&lt;p&gt;The others are the problem, ps90 still waiting on stamp&lt;/p&gt;\n&lt;/div&gt;", "subreddit": "guns", "name": "t1_dgbbh3y", "score_hidden": false, "stickied": false, "created": 1492326469.0, "created_utc": 1492297669.0, "depth": 1, "mod_reports": [], "subreddit_type": "public", "ups": 46}}, {"kind": "t1", "data": {"subreddit_id": "t5_2qhc8", "removal_reason": null, "link_id": "t3_65lkfr", "likes": null, "replies": {"kind": "Listing", "data": {"modhash": "", "children": [{"kind": "t1", "data": {"subreddit_id": "t5_2qhc8", "removal_reason": null, "link_id": "t3_65lkfr", "likes": null, "replies": "", "user_reports": [], "id": "dgbh378", "gilded": 0, "archived": false, "score": 13, "report_reasons": null, "author": "chaumiester", "parent_id": "t1_dgbd6ca", "subreddit_name_prefixed": "r/guns", "controversiality": 0, "body": "Play on words bud. I love any and all armament companies that make good shit", "edited": false, "downs": 0, "body_html": "&lt;div class=\"md\"&gt;&lt;p&gt;Play on words bud. I love any and all armament companies that make good shit&lt;/p&gt;\n&lt;/div&gt;", "subreddit": "guns", "name": "t1_dgbh378", "score_hidden": false, "stickied": false, "created": 1492334437.0, "created_utc": 1492305637.0, "depth": 2, "mod_reports": [], "subreddit_type": "public", "ups": 13}}], "after": null, "before": null}}, "user_reports": [], "id": "dgbd6ca", "gilded": 0, "archived": false, "score": 3, "report_reasons": null, "author": "NavySeal1999", "parent_id": "t1_dgbbfkz", "subreddit_name_prefixed": "r/guns", "controversiality": 1, "body": "FN is kick ass dude. Love most I their guns. Wish to have an FiveSeven pistol and the ps90 in the next two years :P\nWhat armament company do you prefer?", "edited": false, "downs": 0, "body_html": "&lt;div class=\"md\"&gt;&lt;p&gt;FN is kick ass dude. Love most I their guns. Wish to have an FiveSeven pistol and the ps90 in the next two years :P\nWhat armament company do you prefer?&lt;/p&gt;\n&lt;/div&gt;", "subreddit": "guns", "name": "t1_dgbd6ca", "score_hidden": false, "stickied": false, "created": 1492328891.0, "created_utc": 1492300091.0, "depth": 1, "mod_reports": [], "subreddit_type": "public", "ups": 3}}], "after": null, "before": null}}, "user_reports": [], "id": "dgbbfkz", "gilded": 0, "archived": false, "score": 71, "report_reasons": null, "author": "chaumiester", "parent_id": "t3_65lkfr", "subreddit_name_prefixed": "r/guns", "controversiality": 0, "body": "You have a FN problem dude.", "edited": false, "downs": 0, "body_html": "&lt;div class=\"md\"&gt;&lt;p&gt;You have a FN problem dude.&lt;/p&gt;\n&lt;/div&gt;", "subreddit": "guns", "name": "t1_dgbbfkz", "score_hidden": false, "stickied": false, "created": 1492326408.0, "created_utc": 1492297608.0, "depth": 0, "mod_reports": [], "subreddit_type": "public", "ups": 71}}, {"kind": "t1", "data": {"subreddit_id": "t5_2qhc8", "removal_reason": null, "link_id": "t3_65lkfr", "likes": null, "replies": {"kind": "Listing", "data": {"modhash": "", "children": [{"kind": "t1", "data": {"subreddit_id": "t5_2qhc8", "removal_reason": null, "link_id": "t3_65lkfr", "likes": null, "replies": {"kind": "Listing", "data": {"modhash": "", "children": [{"kind": "t1", "data": {"subreddit_id": "t5_2qhc8", "removal_reason": null, "link_id": "t3_65lkfr", "likes": null, "replies": "", "user_reports": [], "id": "dgb8n7o", "gilded": 0, "archived": false, "score": 33, "report_reasons": null, "author": "Not_Vasily", "parent_id": "t1_dgb8lf6", "subreddit_name_prefixed": "r/guns", "controversiality": 0, "body": "real fn' nato.", "edited": false, "downs": 0, "body_html": "&lt;div class=\"md\"&gt;&lt;p&gt;real fn&amp;#39; nato.&lt;/p&gt;\n&lt;/div&gt;", "subreddit": "guns", "name": "t1_dgb8n7o", "score_hidden": false, "stickied": false, "created": 1492322364.0, "created_utc": 1492293564.0, "depth": 2, "mod_reports": [], "subreddit_type": "public", "ups": 33}}, {"kind": "t1", "data": {"subreddit_id": "t5_2qhc8", "removal_reason": null, "link_id": "t3_65lkfr", "likes": null, "replies": {"kind": "Listing", "data": {"modhash": "", "children": [{"kind": "t1", "data": {"subreddit_id": "t5_2qhc8", "removal_reason": null, "link_id": "t3_65lkfr", "likes": null, "replies": {"kind": "Listing", "data": {"modhash": "", "children": [{"kind": "t1", "data": {"subreddit_id": "t5_2qhc8", "removal_reason": null, "link_id": "t3_65lkfr", "likes": null, "replies": {"kind": "Listing", "data": {"modhash": "", "children": [{"kind": "t1", "data": {"subreddit_id": "t5_2qhc8", "removal_reason": null, "link_id": "t3_65lkfr", "likes": null, "replies": "", "user_reports": [], "id": "dgb8urx", "gilded": 0, "archived": false, "score": 2, "report_reasons": null, "author": "fat_italian_stallion", "parent_id": "t1_dgb8tqo", "subreddit_name_prefixed": "r/guns", "controversiality": 0, "body": "not sure when you checked the comment, but edited to clarify on some stuff. Arms mount n stuff. ", "edited": false, "downs": 0, "body_html": "&lt;div class=\"md\"&gt;&lt;p&gt;not sure when you checked the comment, but edited to clarify on some stuff. Arms mount n stuff. &lt;/p&gt;\n&lt;/div&gt;", "subreddit": "guns", "name": "t1_dgb8urx", "score_hidden": false, "stickied": false, "created": 1492322664.0, "created_utc": 1492293864.0, "depth": 5, "mod_reports": [], "subreddit_type": "public", "ups": 2}}], "after": null, "before": null}}, "user_reports": [], "id": "dgb8tqo", "gilded": 0, "archived": false, "score": 2, "report_reasons": null, "author": "-300BlackoutDrunk-", "parent_id": "t1_dgb8rku", "subreddit_name_prefixed": "r/guns", "controversiality": 0, "body": "word", "edited": false, "downs": 0, "body_html": "&lt;div class=\"md\"&gt;&lt;p&gt;word&lt;/p&gt;\n&lt;/div&gt;", "subreddit": "guns", "name": "t1_dgb8tqo", "score_hidden": false, "stickied": false, "created": 1492322623.0, "created_utc": 1492293823.0, "depth": 4, "mod_reports": [], "subreddit_type": "public", "ups": 2}}], "after": null, "before": null}}, "user_reports": [], "id": "dgb8rku", "gilded": 0, "archived": false, "score": 3, "report_reasons": null, "author": "fat_italian_stallion", "parent_id": "t1_dgb8pnp", "subreddit_name_prefixed": "r/guns", "controversiality": 0, "body": "Love it. My only complaint is the illumination when in crosshair mode, it's not visible during the day. Make sure to swap out the standard ARMS levers with MK2 levers. Allows it to adjust to out of spec rails if damage occurs. ", "edited": false, "downs": 0, "body_html": "&lt;div class=\"md\"&gt;&lt;p&gt;Love it. My only complaint is the illumination when in crosshair mode, it&amp;#39;s not visible during the day. Make sure to swap out the standard ARMS levers with MK2 levers. Allows it to adjust to out of spec rails if damage occurs. &lt;/p&gt;\n&lt;/div&gt;", "subreddit": "guns", "name": "t1_dgb8rku", "score_hidden": false, "stickied": false, "created": 1492322538.0, "created_utc": 1492293738.0, "depth": 3, "mod_reports": [], "subreddit_type": "public", "ups": 3}}], "after": null, "before": null}}, "user_reports": [], "id": "dgb8pnp", "gilded": 0, "archived": false, "score": 3, "report_reasons": null, "author": "-300BlackoutDrunk-", "parent_id": "t1_dgb8lf6", "subreddit_name_prefixed": "r/guns", "controversiality": 0, "body": "so you like the elcan? my buddy just got a 17 and needs an optic", "edited": false, "downs": 0, "body_html": "&lt;div class=\"md\"&gt;&lt;p&gt;so you like the elcan? my buddy just got a 17 and needs an optic&lt;/p&gt;\n&lt;/div&gt;", "subreddit": "guns", "name": "t1_dgb8pnp", "score_hidden": false, "stickied": false, "created": 1492322462.0, "created_utc": 1492293662.0, "depth": 2, "mod_reports": [], "subreddit_type": "public", "ups": 3}}], "after": null, "before": null}}, "user_reports": [], "id": "dgb8lf6", "gilded": 0, "archived": false, "score": 11, "report_reasons": null, "author": "fat_italian_stallion", "parent_id": "t1_dgb8jm8", "subreddit_name_prefixed": "r/guns", "controversiality": 0, "body": "neato", "edited": false, "downs": 0, "body_html": "&lt;div class=\"md\"&gt;&lt;p&gt;neato&lt;/p&gt;\n&lt;/div&gt;", "subreddit": "guns", "name": "t1_dgb8lf6", "score_hidden": false, "stickied": false, "created": 1492322293.0, "created_utc": 1492293493.0, "depth": 1, "mod_reports": [], "subreddit_type": "public", "ups": 11}}], "after": null, "before": null}}, "user_reports": [], "id": "dgb8jm8", "gilded": 0, "archived": false, "score": 19, "report_reasons": null, "author": "-300BlackoutDrunk-", "parent_id": "t3_65lkfr", "subreddit_name_prefixed": "r/guns", "controversiality": 0, "body": "neat", "edited": false, "downs": 0, "body_html": "&lt;div class=\"md\"&gt;&lt;p&gt;neat&lt;/p&gt;\n&lt;/div&gt;", "subreddit": "guns", "name": "t1_dgb8jm8", "score_hidden": false, "stickied": false, "created": 1492322225.0, "created_utc": 1492293425.0, "depth": 0, "mod_reports": [], "subreddit_type": "public", "ups": 19}}, {"kind": "t1", "data": {"subreddit_id": "t5_2qhc8", "removal_reason": null, "link_id": "t3_65lkfr", "likes": null, "replies": {"kind": "Listing", "data": {"modhash": "", "children": [{"kind": "t1", "data": {"subreddit_id": "t5_2qhc8", "removal_reason": null, "link_id": "t3_65lkfr", "likes": null, "replies": {"kind": "Listing", "data": {"modhash": "", "children": [{"kind": "t1", "data": {"subreddit_id": "t5_2qhc8", "removal_reason": null, "link_id": "t3_65lkfr", "likes": null, "replies": "", "user_reports": [], "id": "dgbd7wi", "gilded": 0, "archived": false, "score": 12, "report_reasons": null, "author": "Sirflow", "parent_id": "t1_dgba8a2", "subreddit_name_prefixed": "r/guns", "controversiality": 0, "body": "OP said he paid $7k+. Money is no issue. ", "edited": false, "downs": 0, "body_html": "&lt;div class=\"md\"&gt;&lt;p&gt;OP said he paid $7k+. Money is no issue. &lt;/p&gt;\n&lt;/div&gt;", "subreddit": "guns", "name": "t1_dgbd7wi", "score_hidden": false, "stickied": false, "created": 1492328950.0, "created_utc": 1492300150.0, "depth": 2, "mod_reports": [], "subreddit_type": "public", "ups": 12}}, {"kind": "t1", "data": {"subreddit_id": "t5_2qhc8", "removal_reason": null, "link_id": "t3_65lkfr", "likes": null, "replies": "", "user_reports": [], "id": "dgbll9i", "gilded": 0, "archived": false, "score": 2, "report_reasons": null, "author": "pwny_", "parent_id": "t1_dgba8a2", "subreddit_name_prefixed": "r/guns", "controversiality": 0, "body": "Considering what the guns themselves retail for (over 10k all in), ammo money is chump change", "edited": false, "downs": 0, "body_html": "&lt;div class=\"md\"&gt;&lt;p&gt;Considering what the guns themselves retail for (over 10k all in), ammo money is chump change&lt;/p&gt;\n&lt;/div&gt;", "subreddit": "guns", "name": "t1_dgbll9i", "score_hidden": false, "stickied": false, "created": 1492341053.0, "created_utc": 1492312253.0, "depth": 2, "mod_reports": [], "subreddit_type": "public", "ups": 2}}], "after": null, "before": null}}, "user_reports": [], "id": "dgba8a2", "gilded": 0, "archived": false, "score": 24, "report_reasons": null, "author": "RescueRandyMD", "parent_id": "t1_dgb7hrx", "subreddit_name_prefixed": "r/guns", "controversiality": 0, "body": "&gt;The ammo seems to last forever\n\nTill your wallet screams at you to pound sand... but if you have a M249 money isnt an  issue?", "edited": false, "downs": 0, "body_html": "&lt;div class=\"md\"&gt;&lt;blockquote&gt;\n&lt;p&gt;The ammo seems to last forever&lt;/p&gt;\n&lt;/blockquote&gt;\n\n&lt;p&gt;Till your wallet screams at you to pound sand... but if you have a M249 money isnt an  issue?&lt;/p&gt;\n&lt;/div&gt;", "subreddit": "guns", "name": "t1_dgba8a2", "score_hidden": false, "stickied": false, "created": 1492324634.0, "created_utc": 1492295834.0, "depth": 1, "mod_reports": [], "subreddit_type": "public", "ups": 24}}, {"kind": "t1", "data": {"subreddit_id": "t5_2qhc8", "removal_reason": null, "link_id": "t3_65lkfr", "likes": null, "replies": {"kind": "Listing", "data": {"modhash": "", "children": [{"kind": "t1", "data": {"subreddit_id": "t5_2qhc8", "removal_reason": null, "link_id": "t3_65lkfr", "likes": null, "replies": {"kind": "Listing", "data": {"modhash": "", "children": [{"kind": "t1", "data": {"subreddit_id": "t5_2qhc8", "removal_reason": null, "link_id": "t3_65lkfr", "likes": null, "replies": {"kind": "Listing", "data": {"modhash": "", "children": [{"kind": "t1", "data": {"subreddit_id": "t5_2qhc8", "removal_reason": null, "link_id": "t3_65lkfr", "likes": null, "replies": {"kind": "Listing", "data": {"modhash": "", "children": [{"kind": "t1", "data": {"subreddit_id": "t5_2qhc8", "removal_reason": null, "link_id": "t3_65lkfr", "likes": null, "replies": "", "user_reports": [], "id": "dgbkqhh", "gilded": 0, "archived": false, "score": 1, "report_reasons": null, "author": "LeadBased", "parent_id": "t1_dgbkf1k", "subreddit_name_prefixed": "r/guns", "controversiality": 0, "body": "Thanks for the clarification.", "edited": false, "downs": 0, "body_html": "&lt;div class=\"md\"&gt;&lt;p&gt;Thanks for the clarification.&lt;/p&gt;\n&lt;/div&gt;", "subreddit": "guns", "name": "t1_dgbkqhh", "score_hidden": false, "stickied": false, "created": 1492339795.0, "created_utc": 1492310995.0, "depth": 5, "mod_reports": [], "subreddit_type": "public", "ups": 1}}, {"kind": "t1", "data": {"subreddit_id": "t5_2qhc8", "removal_reason": null, "link_id": "t3_65lkfr", "likes": null, "replies": "", "user_reports": [], "id": "dgboqkd", "gilded": 0, "archived": false, "score": 1, "report_reasons": null, "author": "fooddood", "parent_id": "t1_dgbkf1k", "subreddit_name_prefixed": "r/guns", "controversiality": 0, "body": "You can also get an FFL to sell new machine guns to Law Enforcement agencies", "edited": false, "downs": 0, "body_html": "&lt;div class=\"md\"&gt;&lt;p&gt;You can also get an FFL to sell new machine guns to Law Enforcement agencies&lt;/p&gt;\n&lt;/div&gt;", "subreddit": "guns", "name": "t1_dgboqkd", "score_hidden": false, "stickied": false, "created": 1492346139.0, "created_utc": 1492317339.0, "depth": 5, "mod_reports": [], "subreddit_type": "public", "ups": 1}}], "after": null, "before": null}}, "user_reports": [], "id": "dgbkf1k", "gilded": 0, "archived": false, "score": 6, "report_reasons": null, "author": "gijose41", "parent_id": "t1_dgbip64", "subreddit_name_prefixed": "r/guns", "controversiality": 0, "body": "What you see in that picture is no LMG. It is a belt fed semi-automatic rifle. \n\nTo acquire machine gun, it must be registered and manufactured before 1986 and be transferred along with a special tax stamp. Another path is to apply for a special FFL that allows you to manufacture machine guns for PD or military use. ", "edited": false, "downs": 0, "body_html": "&lt;div class=\"md\"&gt;&lt;p&gt;What you see in that picture is no LMG. It is a belt fed semi-automatic rifle. &lt;/p&gt;\n\n&lt;p&gt;To acquire machine gun, it must be registered and manufactured before 1986 and be transferred along with a special tax stamp. Another path is to apply for a special FFL that allows you to manufacture machine guns for PD or military use. &lt;/p&gt;\n&lt;/div&gt;", "subreddit": "guns", "name": "t1_dgbkf1k", "score_hidden": false, "stickied": false, "created": 1492339335.0, "created_utc": 1492310535.0, "depth": 4, "mod_reports": [], "subreddit_type": "public", "ups": 6}}, {"kind": "t1", "data": {"subreddit_id": "t5_2qhc8", "removal_reason": null, "link_id": "t3_65lkfr", "likes": null, "replies": "", "user_reports": [], "id": "dgbjb3f", "gilded": 0, "archived": false, "score": 1, "report_reasons": null, "author": "ThePewPew1337", "parent_id": "t1_dgbip64", "subreddit_name_prefixed": "r/guns", "controversiality": 0, "body": "Not hard, unless it's full auto.", "edited": false, "downs": 0, "body_html": "&lt;div class=\"md\"&gt;&lt;p&gt;Not hard, unless it&amp;#39;s full auto.&lt;/p&gt;\n&lt;/div&gt;", "subreddit": "guns", "name": "t1_dgbjb3f", "score_hidden": false, "stickied": false, "created": 1492337689.0, "created_utc": 1492308889.0, "depth": 4, "mod_reports": [], "subreddit_type": "public", "ups": 1}}], "after": null, "before": null}}, "user_reports": [], "id": "dgbip64", "gilded": 0, "archived": false, "score": 2, "report_reasons": null, "author": "LeadBased", "parent_id": "t1_dgb9lis", "subreddit_name_prefixed": "r/guns", "controversiality": 0, "body": "Canadian here: how difficult is it to get an LMG and is it full auto?\n\nAlso can we be friends? I'll bring the ammo.", "edited": false, "downs": 0, "body_html": "&lt;div class=\"md\"&gt;&lt;p&gt;Canadian here: how difficult is it to get an LMG and is it full auto?&lt;/p&gt;\n\n&lt;p&gt;Also can we be friends? I&amp;#39;ll bring the ammo.&lt;/p&gt;\n&lt;/div&gt;", "subreddit": "guns", "name": "t1_dgbip64", "score_hidden": false, "stickied": false, "created": 1492336791.0, "created_utc": 1492307991.0, "depth": 3, "mod_reports": [], "subreddit_type": "public", "ups": 2}}], "after": null, "before": null}}, "user_reports": [], "id": "dgb9lis", "gilded": 0, "archived": false, "score": 16, "report_reasons": null, "author": "fat_italian_stallion", "parent_id": "t1_dgb9gzw", "subreddit_name_prefixed": "r/guns", "controversiality": 0, "body": "$7,135 shipped, no xfer fee. ", "edited": false, "downs": 0, "body_html": "&lt;div class=\"md\"&gt;&lt;p&gt;$7,135 shipped, no xfer fee. &lt;/p&gt;\n&lt;/div&gt;", "subreddit": "guns", "name": "t1_dgb9lis", "score_hidden": false, "stickied": false, "created": 1492323711.0, "created_utc": 1492294911.0, "depth": 2, "mod_reports": [], "subreddit_type": "public", "ups": 16}}], "after": null, "before": null}}, "user_reports": [], "id": "dgb9gzw", "gilded": 0, "archived": false, "score": 7, "report_reasons": null, "author": "BenjiSalami", "parent_id": "t1_dgb7hrx", "subreddit_name_prefixed": "r/guns", "controversiality": 0, "body": "How much did you pay for the saw if you dont mind me asking", "edited": false, "downs": 0, "body_html": "&lt;div class=\"md\"&gt;&lt;p&gt;How much did you pay for the saw if you dont mind me asking&lt;/p&gt;\n&lt;/div&gt;", "subreddit": "guns", "name": "t1_dgb9gzw", "score_hidden": false, "stickied": false, "created": 1492323534.0, "created_utc": 1492294734.0, "depth": 1, "mod_reports": [], "subreddit_type": "public", "ups": 7}}, {"kind": "t1", "data": {"subreddit_id": "t5_2qhc8", "removal_reason": null, "link_id": "t3_65lkfr", "likes": null, "replies": {"kind": "Listing", "data": {"modhash": "", "children": [{"kind": "t1", "data": {"subreddit_id": "t5_2qhc8", "removal_reason": null, "link_id": "t3_65lkfr", "likes": null, "replies": {"kind": "Listing", "data": {"modhash": "", "children": [{"kind": "t1", "data": {"subreddit_id": "t5_2qhc8", "removal_reason": null, "link_id": "t3_65lkfr", "likes": null, "replies": {"kind": "Listing", "data": {"modhash": "", "children": [{"kind": "t1", "data": {"subreddit_id": "t5_2qhc8", "removal_reason": null, "link_id": "t3_65lkfr", "likes": null, "replies": "", "user_reports": [], "id": "dgbfnsp", "gilded": 0, "archived": false, "score": 5, "report_reasons": null, "author": "fat_italian_stallion", "parent_id": "t1_dgbf1fa", "subreddit_name_prefixed": "r/guns", "controversiality": 0, "body": "Ammo goes fast enough as is", "edited": false, "downs": 0, "body_html": "&lt;div class=\"md\"&gt;&lt;p&gt;Ammo goes fast enough as is&lt;/p&gt;\n&lt;/div&gt;", "subreddit": "guns", "name": "t1_dgbfnsp", "score_hidden": false, "stickied": false, "created": 1492332420.0, "created_utc": 1492303620.0, "depth": 4, "mod_reports": [], "subreddit_type": "public", "ups": 5}}], "after": null, "before": null}}, "user_reports": [], "id": "dgbf1fa", "gilded": 0, "archived": false, "score": 3, "report_reasons": null, "author": "NavySeal1999", "parent_id": "t1_dgbe3bb", "subreddit_name_prefixed": "r/guns", "controversiality": 0, "body": "Awesome. Hey you should get a crank for it. You know one of those Gatling cranks", "edited": false, "downs": 0, "body_html": "&lt;div class=\"md\"&gt;&lt;p&gt;Awesome. Hey you should get a crank for it. You know one of those Gatling cranks&lt;/p&gt;\n&lt;/div&gt;", "subreddit": "guns", "name": "t1_dgbf1fa", "score_hidden": false, "stickied": false, "created": 1492331531.0, "created_utc": 1492302731.0, "depth": 3, "mod_reports": [], "subreddit_type": "public", "ups": 3}}, {"kind": "t1", "data": {"subreddit_id": "t5_2qhc8", "removal_reason": null, "link_id": "t3_65lkfr", "likes": null, "replies": {"kind": "Listing", "data": {"modhash": "", "children": [{"kind": "t1", "data": {"subreddit_id": "t5_2qhc8", "removal_reason": null, "link_id": "t3_65lkfr", "likes": null, "replies": "", "user_reports": [], "id": "dgc6uq3", "gilded": 0, "archived": false, "score": 1, "report_reasons": null, "author": "frthood", "parent_id": "t1_dgbfpeu", "subreddit_name_prefixed": "r/guns", "controversiality": 0, "body": "Usually jams on mags, too.", "edited": false, "downs": 0, "body_html": "&lt;div class=\"md\"&gt;&lt;p&gt;Usually jams on mags, too.&lt;/p&gt;\n&lt;/div&gt;", "subreddit": "guns", "name": "t1_dgc6uq3", "score_hidden": false, "stickied": false, "created": 1492387297.0, "created_utc": 1492358497.0, "depth": 4, "mod_reports": [], "subreddit_type": "public", "ups": 1}}], "after": null, "before": null}}, "user_reports": [], "id": "dgbfpeu", "gilded": 0, "archived": false, "score": 2, "report_reasons": null, "author": "MyOldNameSucked", "parent_id": "t1_dgbe3bb", "subreddit_name_prefixed": "r/guns", "controversiality": 0, "body": "I heard it likes to destroy mags and you are only supposed to use it if you are out of belts and in deep trouble.", "edited": false, "downs": 0, "body_html": "&lt;div class=\"md\"&gt;&lt;p&gt;I heard it likes to destroy mags and you are only supposed to use it if you are out of belts and in deep trouble.&lt;/p&gt;\n&lt;/div&gt;", "subreddit": "guns", "name": "t1_dgbfpeu", "score_hidden": false, "stickied": false, "created": 1492332480.0, "created_utc": 1492303680.0, "depth": 3, "mod_reports": [], "subreddit_type": "public", "ups": 2}}], "after": null, "before": null}}, "user_reports": [], "id": "dgbe3bb", "gilded": 0, "archived": false, "score": 4, "report_reasons": null, "author": "fat_italian_stallion", "parent_id": "t1_dgbd9g5", "subreddit_name_prefixed": "r/guns", "controversiality": 0, "body": "Worth it every penny.  I link it myself. Links are $0.04 each if you buy 5k at a time. It can use mags. Haven't tried yet", "edited": false, "downs": 0, "body_html": "&lt;div class=\"md\"&gt;&lt;p&gt;Worth it every penny.  I link it myself. Links are $0.04 each if you buy 5k at a time. It can use mags. Haven&amp;#39;t tried yet&lt;/p&gt;\n&lt;/div&gt;", "subreddit": "guns", "name": "t1_dgbe3bb", "score_hidden": false, "stickied": false, "created": 1492330139.0, "created_utc": 1492301339.0, "depth": 2, "mod_reports": [], "subreddit_type": "public", "ups": 4}}], "after": null, "before": null}}, "user_reports": [], "id": "dgbd9g5", "gilded": 0, "archived": false, "score": 4, "report_reasons": null, "author": "NavySeal1999", "parent_id": "t1_dgb7hrx", "subreddit_name_prefixed": "r/guns", "controversiality": 0, "body": "Do you think it is worth buying the m249? How much does it cost to buy the ammo in belts? Also can't the m249 use standard AR mags too?", "edited": false, "downs": 0, "body_html": "&lt;div class=\"md\"&gt;&lt;p&gt;Do you think it is worth buying the m249? How much does it cost to buy the ammo in belts? Also can&amp;#39;t the m249 use standard AR mags too?&lt;/p&gt;\n&lt;/div&gt;", "subreddit": "guns", "name": "t1_dgbd9g5", "score_hidden": false, "stickied": false, "created": 1492329007.0, "created_utc": 1492300207.0, "depth": 1, "mod_reports": [], "subreddit_type": "public", "ups": 4}}, {"kind": "t1", "data": {"subreddit_id": "t5_2qhc8", "removal_reason": null, "link_id": "t3_65lkfr", "likes": null, "replies": "", "user_reports": [], "id": "dgblroa", "gilded": 0, "archived": false, "score": 2, "report_reasons": null, "author": "SemperFiGuy", "parent_id": "t1_dgb7hrx", "subreddit_name_prefixed": "r/guns", "controversiality": 0, "body": "Consider a Trijicon SDO for your SAW. It's what the USMC uses on ours.", "edited": false, "downs": 0, "body_html": "&lt;div class=\"md\"&gt;&lt;p&gt;Consider a Trijicon SDO for your SAW. It&amp;#39;s what the USMC uses on ours.&lt;/p&gt;\n&lt;/div&gt;", "subreddit": "guns", "name": "t1_dgblroa", "score_hidden": false, "stickied": false, "created": 1492341323.0, "created_utc": 1492312523.0, "depth": 1, "mod_reports": [], "subreddit_type": "public", "ups": 2}}], "after": null, "before": null}}, "user_reports": [], "id": "dgb7hrx", "gilded": 0, "archived": false, "score": 17, "report_reasons": null, "author": "fat_italian_stallion", "parent_id": "t3_65lkfr", "subreddit_name_prefixed": "r/guns", "controversiality": 0, "body": "Since there's always some kind of day of the week shitpost I thought I'd join in. Below you have some of my guns that start with \"S\" and it's Saturday. The scars get the most use out of any of the guns in my collection. Well over 10K through the 16s and somewhere near 7k through the 17s. The Saw is quickly on its way to beat both of them, having only gone to 2 range sessions and very close to 2k. So far the scars are by far the most reliable guns in my collection as well. The only failure I've had out of either of them was a squib from Perfecta ammo in my 16s. Thankfully I caught it or the gun might not be here today. \n\n**SCAR 16s:** The gun that started my love-hate relationship with FN products. My goal with this gun is to keep it relatively light and maneuverable. So far so good. The PMM parts really help keep weight down compared to the OEM pic rails. Future plan is to add an Elcan Specter 1.0-4.0x, swap out charging handle for Stryker each, swap out the Ergo grip for a PMM modified FDE MOE+, and SiCo Saker 5.56\n\nCurrent parts: \n\n* Geissele Super Scar\n\n* Aimpoint Comp M4S w/ Larue QD Mount\n\n* Ergo Grip\n\n* PMM HD MLOK Handguard\n\n* PMM Mlok side panels\n\n* PMM Mlok lower panel\n\n* Magpul type 2 mlok covers\n\n* Magpuy Mlok grip\n\n* Magpul Mlok hand stop\n\n* Larue Index clips\n\n* PMM front and read QD slingpoints\n\n* PMM Safety Selectors\n\n* PMM Extended Mag Release\n\n**SCAR 17s:** The gun I always put newcomers on when we head to knob creek. It really builds confidence being able to hit at 300 without any effort. That being said, I really wish there was a place I could stretch it out. Future plan is to PMM out the gun similar to my 16s, grab a Stryker FDE anodized Atlast BT10, swap out IWC scar charger for stryker each, swap out the Ergo grip for a PMM modified FDE MOE+, SiCO Saker 7.62, and SiCo Radius.\n\nCurrent parts: \n* Geissele Super Scar\n\n* Elcan Specter Dr 1.5-6.0x\n\n* Ergo Grip\n\n* Atlas BT10 Bipod\n\n* Largue Index clips\n\n* PMM Safety Selectors\n\n* IWC Scar charger\n\n* PMM Extended Mag Release\n\n**M249S SAW:** Easily the most fun non-giggle gun I've fired. The ammo seems to last forever. The trigger is pretty good for what it is, making rapid fire a blast. I put around 800 through it just by myself last range session. It's going to live a hard life. Only negative is clean up later. Pretty sure I could have made a few casing from all of the shaved brass. Future plan is to swap the Eotech for either an Elcan M145 or a Trijicon Acog MGO optic, replace the handguard with the MGA railed version from the MK46 and replace the bipod with the improved Saw bipod. \n\nCurrent parts: \n\n* EXPS3-0\n\n", "edited": 1492293457.0, "downs": 0, "body_html": "&lt;div class=\"md\"&gt;&lt;p&gt;Since there&amp;#39;s always some kind of day of the week shitpost I thought I&amp;#39;d join in. Below you have some of my guns that start with &amp;quot;S&amp;quot; and it&amp;#39;s Saturday. The scars get the most use out of any of the guns in my collection. Well over 10K through the 16s and somewhere near 7k through the 17s. The Saw is quickly on its way to beat both of them, having only gone to 2 range sessions and very close to 2k. So far the scars are by far the most reliable guns in my collection as well. The only failure I&amp;#39;ve had out of either of them was a squib from Perfecta ammo in my 16s. Thankfully I caught it or the gun might not be here today. &lt;/p&gt;\n\n&lt;p&gt;&lt;strong&gt;SCAR 16s:&lt;/strong&gt; The gun that started my love-hate relationship with FN products. My goal with this gun is to keep it relatively light and maneuverable. So far so good. The PMM parts really help keep weight down compared to the OEM pic rails. Future plan is to add an Elcan Specter 1.0-4.0x, swap out charging handle for Stryker each, swap out the Ergo grip for a PMM modified FDE MOE+, and SiCo Saker 5.56&lt;/p&gt;\n\n&lt;p&gt;Current parts: &lt;/p&gt;\n\n&lt;ul&gt;\n&lt;li&gt;&lt;p&gt;Geissele Super Scar&lt;/p&gt;&lt;/li&gt;\n&lt;li&gt;&lt;p&gt;Aimpoint Comp M4S w/ Larue QD Mount&lt;/p&gt;&lt;/li&gt;\n&lt;li&gt;&lt;p&gt;Ergo Grip&lt;/p&gt;&lt;/li&gt;\n&lt;li&gt;&lt;p&gt;PMM HD MLOK Handguard&lt;/p&gt;&lt;/li&gt;\n&lt;li&gt;&lt;p&gt;PMM Mlok side panels&lt;/p&gt;&lt;/li&gt;\n&lt;li&gt;&lt;p&gt;PMM Mlok lower panel&lt;/p&gt;&lt;/li&gt;\n&lt;li&gt;&lt;p&gt;Magpul type 2 mlok covers&lt;/p&gt;&lt;/li&gt;\n&lt;li&gt;&lt;p&gt;Magpuy Mlok grip&lt;/p&gt;&lt;/li&gt;\n&lt;li&gt;&lt;p&gt;Magpul Mlok hand stop&lt;/p&gt;&lt;/li&gt;\n&lt;li&gt;&lt;p&gt;Larue Index clips&lt;/p&gt;&lt;/li&gt;\n&lt;li&gt;&lt;p&gt;PMM front and read QD slingpoints&lt;/p&gt;&lt;/li&gt;\n&lt;li&gt;&lt;p&gt;PMM Safety Selectors&lt;/p&gt;&lt;/li&gt;\n&lt;li&gt;&lt;p&gt;PMM Extended Mag Release&lt;/p&gt;&lt;/li&gt;\n&lt;/ul&gt;\n\n&lt;p&gt;&lt;strong&gt;SCAR 17s:&lt;/strong&gt; The gun I always put newcomers on when we head to knob creek. It really builds confidence being able to hit at 300 without any effort. That being said, I really wish there was a place I could stretch it out. Future plan is to PMM out the gun similar to my 16s, grab a Stryker FDE anodized Atlast BT10, swap out IWC scar charger for stryker each, swap out the Ergo grip for a PMM modified FDE MOE+, SiCO Saker 7.62, and SiCo Radius.&lt;/p&gt;\n\n&lt;p&gt;Current parts: \n* Geissele Super Scar&lt;/p&gt;\n\n&lt;ul&gt;\n&lt;li&gt;&lt;p&gt;Elcan Specter Dr 1.5-6.0x&lt;/p&gt;&lt;/li&gt;\n&lt;li&gt;&lt;p&gt;Ergo Grip&lt;/p&gt;&lt;/li&gt;\n&lt;li&gt;&lt;p&gt;Atlas BT10 Bipod&lt;/p&gt;&lt;/li&gt;\n&lt;li&gt;&lt;p&gt;Largue Index clips&lt;/p&gt;&lt;/li&gt;\n&lt;li&gt;&lt;p&gt;PMM Safety Selectors&lt;/p&gt;&lt;/li&gt;\n&lt;li&gt;&lt;p&gt;IWC Scar charger&lt;/p&gt;&lt;/li&gt;\n&lt;li&gt;&lt;p&gt;PMM Extended Mag Release&lt;/p&gt;&lt;/li&gt;\n&lt;/ul&gt;\n\n&lt;p&gt;&lt;strong&gt;M249S SAW:&lt;/strong&gt; Easily the most fun non-giggle gun I&amp;#39;ve fired. The ammo seems to last forever. The trigger is pretty good for what it is, making rapid fire a blast. I put around 800 through it just by myself last range session. It&amp;#39;s going to live a hard life. Only negative is clean up later. Pretty sure I could have made a few casing from all of the shaved brass. Future plan is to swap the Eotech for either an Elcan M145 or a Trijicon Acog MGO optic, replace the handguard with the MGA railed version from the MK46 and replace the bipod with the improved Saw bipod. &lt;/p&gt;\n\n&lt;p&gt;Current parts: &lt;/p&gt;\n\n&lt;ul&gt;\n&lt;li&gt;EXPS3-0&lt;/li&gt;\n&lt;/ul&gt;\n&lt;/div&gt;", "subreddit": "guns", "name": "t1_dgb7hrx", "score_hidden": false, "stickied": false, "created": 1492320784.0, "created_utc": 1492291984.0, "depth": 0, "mod_reports": [], "subreddit_type": "public", "ups": 17}}, {"kind": "t1", "data": {"subreddit_id": "t5_2qhc8", "removal_reason": null, "link_id": "t3_65lkfr", "likes": null, "replies": {"kind": "Listing", "data": {"modhash": "", "children": [{"kind": "t1", "data": {"subreddit_id": "t5_2qhc8", "removal_reason": null, "link_id": "t3_65lkfr", "likes": null, "replies": {"kind": "Listing", "data": {"modhash": "", "children": [{"kind": "t1", "data": {"subreddit_id": "t5_2qhc8", "removal_reason": null, "link_id": "t3_65lkfr", "likes": null, "replies": "", "user_reports": [], "id": "dgbggeb", "gilded": 0, "archived": false, "score": 4, "report_reasons": null, "author": "Southernlead", "parent_id": "t1_dgbftd0", "subreddit_name_prefixed": "r/guns", "controversiality": 0, "body": "Thanks, space tuna is boner material", "edited": false, "downs": 0, "body_html": "&lt;div class=\"md\"&gt;&lt;p&gt;Thanks, space tuna is boner material&lt;/p&gt;\n&lt;/div&gt;", "subreddit": "guns", "name": "t1_dgbggeb", "score_hidden": false, "stickied": false, "created": 1492333524.0, "created_utc": 1492304724.0, "depth": 2, "mod_reports": [], "subreddit_type": "public", "ups": 4}}], "after": null, "before": null}}, "user_reports": [], "id": "dgbftd0", "gilded": 0, "archived": false, "score": 4, "report_reasons": null, "author": "_2na", "parent_id": "t1_dgbexy8", "subreddit_name_prefixed": "r/guns", "controversiality": 0, "body": "FN FS2000", "edited": false, "downs": 0, "body_html": "&lt;div class=\"md\"&gt;&lt;p&gt;FN FS2000&lt;/p&gt;\n&lt;/div&gt;", "subreddit": "guns", "name": "t1_dgbftd0", "score_hidden": false, "stickied": false, "created": 1492332631.0, "created_utc": 1492303831.0, "depth": 1, "mod_reports": [], "subreddit_type": "public", "ups": 4}}], "after": null, "before": null}}, "user_reports": [], "id": "dgbexy8", "gilded": 0, "archived": false, "score": 2, "report_reasons": null, "author": "Southernlead", "parent_id": "t3_65lkfr", "subreddit_name_prefixed": "r/guns", "controversiality": 0, "body": "My grail gun spot is shared with a scar and a fn fs2000. ", "edited": 1492304709.0, "downs": 0, "body_html": "&lt;div class=\"md\"&gt;&lt;p&gt;My grail gun spot is shared with a scar and a fn fs2000. &lt;/p&gt;\n&lt;/div&gt;", "subreddit": "guns", "name": "t1_dgbexy8", "score_hidden": false, "stickied": false, "created": 1492331389.0, "created_utc": 1492302589.0, "depth": 0, "mod_reports": [], "subreddit_type": "public", "ups": 2}}, {"kind": "t1", "data": {"subreddit_id": "t5_2qhc8", "removal_reason": null, "link_id": "t3_65lkfr", "likes": null, "replies": {"kind": "Listing", "data": {"modhash": "", "children": [{"kind": "t1", "data": {"subreddit_id": "t5_2qhc8", "removal_reason": null, "link_id": "t3_65lkfr", "likes": null, "replies": "", "user_reports": [], "id": "dgbkr2g", "gilded": 0, "archived": false, "score": 3, "report_reasons": null, "author": "fat_italian_stallion", "parent_id": "t1_dgbid4e", "subreddit_name_prefixed": "r/guns", "controversiality": 0, "body": "Hard pass. No bang is worth a scar", "edited": false, "downs": 0, "body_html": "&lt;div class=\"md\"&gt;&lt;p&gt;Hard pass. No bang is worth a scar&lt;/p&gt;\n&lt;/div&gt;", "subreddit": "guns", "name": "t1_dgbkr2g", "score_hidden": false, "stickied": false, "created": 1492339817.0, "created_utc": 1492311017.0, "depth": 1, "mod_reports": [], "subreddit_type": "public", "ups": 3}}], "after": null, "before": null}}, "user_reports": [], "id": "dgbid4e", "gilded": 0, "archived": false, "score": 3, "report_reasons": null, "author": "Ellijah92", "parent_id": "t3_65lkfr", "subreddit_name_prefixed": "r/guns", "controversiality": 0, "body": "I'll let you have me if you give me that SCAR17 as payment. ", "edited": false, "downs": 0, "body_html": "&lt;div class=\"md\"&gt;&lt;p&gt;I&amp;#39;ll let you have me if you give me that SCAR17 as payment. &lt;/p&gt;\n&lt;/div&gt;", "subreddit": "guns", "name": "t1_dgbid4e", "score_hidden": false, "stickied": false, "created": 1492336288.0, "created_utc": 1492307488.0, "depth": 0, "mod_reports": [], "subreddit_type": "public", "ups": 3}}, {"kind": "t1", "data": {"subreddit_id": "t5_2qhc8", "removal_reason": null, "link_id": "t3_65lkfr", "likes": null, "replies": "", "user_reports": [], "id": "dgbloxd", "gilded": 0, "archived": false, "score": 3, "report_reasons": null, "author": "rider037", "parent_id": "t3_65lkfr", "subreddit_name_prefixed": "r/guns", "controversiality": 0, "body": "I love how you remodeled the kitchen. The belt fed really ties it all together!!", "edited": false, "downs": 0, "body_html": "&lt;div class=\"md\"&gt;&lt;p&gt;I love how you remodeled the kitchen. The belt fed really ties it all together!!&lt;/p&gt;\n&lt;/div&gt;", "subreddit": "guns", "name": "t1_dgbloxd", "score_hidden": false, "stickied": false, "created": 1492341207.0, "created_utc": 1492312407.0, "depth": 0, "mod_reports": [], "subreddit_type": "public", "ups": 3}}, {"kind": "t1", "data": {"subreddit_id": "t5_2qhc8", "removal_reason": null, "link_id": "t3_65lkfr", "likes": null, "replies": "", "user_reports": [], "id": "dgbki0p", "gilded": 0, "archived": false, "score": 2, "report_reasons": null, "author": "SimpleinSeattle", "parent_id": "t3_65lkfr", "subreddit_name_prefixed": "r/guns", "controversiality": 0, "body": "I don't typically get jealous about other people's guns...but I'm jealous.  :)\n\nNice bro!  Well done.", "edited": false, "downs": 0, "body_html": "&lt;div class=\"md\"&gt;&lt;p&gt;I don&amp;#39;t typically get jealous about other people&amp;#39;s guns...but I&amp;#39;m jealous.  :)&lt;/p&gt;\n\n&lt;p&gt;Nice bro!  Well done.&lt;/p&gt;\n&lt;/div&gt;", "subreddit": "guns", "name": "t1_dgbki0p", "score_hidden": false, "stickied": false, "created": 1492339453.0, "created_utc": 1492310653.0, "depth": 0, "mod_reports": [], "subreddit_type": "public", "ups": 2}}, {"kind": "t1", "data": {"subreddit_id": "t5_2qhc8", "removal_reason": null, "link_id": "t3_65lkfr", "likes": null, "replies": "", "user_reports": [], "id": "dgbnr77", "gilded": 0, "archived": false, "score": 2, "report_reasons": null, "author": "snayperskaya", "parent_id": "t3_65lkfr", "subreddit_name_prefixed": "r/guns", "controversiality": 0, "body": "Well done, consigliere. ", "edited": false, "downs": 0, "body_html": "&lt;div class=\"md\"&gt;&lt;p&gt;Well done, consigliere. &lt;/p&gt;\n&lt;/div&gt;", "subreddit": "guns", "name": "t1_dgbnr77", "score_hidden": false, "stickied": false, "created": 1492344445.0, "created_utc": 1492315645.0, "depth": 0, "mod_reports": [], "subreddit_type": "public", "ups": 2}}, {"kind": "t1", "data": {"subreddit_id": "t5_2qhc8", "removal_reason": null, "link_id": "t3_65lkfr", "likes": null, "replies": {"kind": "Listing", "data": {"modhash": "", "children": [{"kind": "t1", "data": {"subreddit_id": "t5_2qhc8", "removal_reason": null, "link_id": "t3_65lkfr", "likes": null, "replies": {"kind": "Listing", "data": {"modhash": "", "children": [{"kind": "t1", "data": {"subreddit_id": "t5_2qhc8", "removal_reason": null, "link_id": "t3_65lkfr", "likes": null, "replies": "", "user_reports": [], "id": "dgbx81f", "gilded": 0, "archived": false, "score": 4, "report_reasons": null, "author": "HingelMcCringelBarry", "parent_id": "t1_dgbrd3n", "subreddit_name_prefixed": "r/guns", "controversiality": 0, "body": "The safe in your kitchen next to the fridge would also directly indicate that you are not married. That would not fly at any married man's home. ", "edited": false, "downs": 0, "body_html": "&lt;div class=\"md\"&gt;&lt;p&gt;The safe in your kitchen next to the fridge would also directly indicate that you are not married. That would not fly at any married man&amp;#39;s home. &lt;/p&gt;\n&lt;/div&gt;", "subreddit": "guns", "name": "t1_dgbx81f", "score_hidden": false, "stickied": false, "created": 1492368859.0, "created_utc": 1492340059.0, "depth": 2, "mod_reports": [], "subreddit_type": "public", "ups": 4}}], "after": null, "before": null}}, "user_reports": [], "id": "dgbrd3n", "gilded": 0, "archived": false, "score": 6, "report_reasons": null, "author": "fat_italian_stallion", "parent_id": "t1_dgbpo7u", "subreddit_name_prefixed": "r/guns", "controversiality": 0, "body": "To young for that shit. 5 \"B\"s of London from in order: Bentley, boat, butler, bitch, baby. The latter cannot prevent you from having the former", "edited": false, "downs": 0, "body_html": "&lt;div class=\"md\"&gt;&lt;p&gt;To young for that shit. 5 &amp;quot;B&amp;quot;s of London from in order: Bentley, boat, butler, bitch, baby. The latter cannot prevent you from having the former&lt;/p&gt;\n&lt;/div&gt;", "subreddit": "guns", "name": "t1_dgbrd3n", "score_hidden": false, "stickied": false, "created": 1492351221.0, "created_utc": 1492322421.0, "depth": 1, "mod_reports": [], "subreddit_type": "public", "ups": 6}}], "after": null, "before": null}}, "user_reports": [], "id": "dgbpo7u", "gilded": 0, "archived": false, "score": 2, "report_reasons": null, "author": "JMS144", "parent_id": "t3_65lkfr", "subreddit_name_prefixed": "r/guns", "controversiality": 0, "body": "OP, will you be my father?", "edited": false, "downs": 0, "body_html": "&lt;div class=\"md\"&gt;&lt;p&gt;OP, will you be my father?&lt;/p&gt;\n&lt;/div&gt;", "subreddit": "guns", "name": "t1_dgbpo7u", "score_hidden": false, "stickied": false, "created": 1492347838.0, "created_utc": 1492319038.0, "depth": 0, "mod_reports": [], "subreddit_type": "public", "ups": 2}}, {"kind": "t1", "data": {"subreddit_id": "t5_2qhc8", "removal_reason": null, "link_id": "t3_65lkfr", "likes": null, "replies": {"kind": "Listing", "data": {"modhash": "", "children": [{"kind": "t1", "data": {"subreddit_id": "t5_2qhc8", "removal_reason": null, "link_id": "t3_65lkfr", "likes": null, "replies": "", "user_reports": [], "id": "dgbg3pp", "gilded": 0, "archived": false, "score": 2, "report_reasons": null, "author": "fat_italian_stallion", "parent_id": "t1_dgbfvmw", "subreddit_name_prefixed": "r/guns", "controversiality": 0, "body": "Saving for mk48", "edited": false, "downs": 0, "body_html": "&lt;div class=\"md\"&gt;&lt;p&gt;Saving for mk48&lt;/p&gt;\n&lt;/div&gt;", "subreddit": "guns", "name": "t1_dgbg3pp", "score_hidden": false, "stickied": false, "created": 1492333037.0, "created_utc": 1492304237.0, "depth": 1, "mod_reports": [], "subreddit_type": "public", "ups": 2}}], "after": null, "before": null}}, "user_reports": [], "id": "dgbfvmw", "gilded": 0, "archived": false, "score": 1, "report_reasons": null, "author": "blackhawk905", "parent_id": "t3_65lkfr", "subreddit_name_prefixed": "r/guns", "controversiality": 0, "body": "You just need an M240 now.", "edited": false, "downs": 0, "body_html": "&lt;div class=\"md\"&gt;&lt;p&gt;You just need an M240 now.&lt;/p&gt;\n&lt;/div&gt;", "subreddit": "guns", "name": "t1_dgbfvmw", "score_hidden": false, "stickied": false, "created": 1492332718.0, "created_utc": 1492303918.0, "depth": 0, "mod_reports": [], "subreddit_type": "public", "ups": 1}}, {"kind": "t1", "data": {"subreddit_id": "t5_2qhc8", "removal_reason": null, "link_id": "t3_65lkfr", "likes": null, "replies": "", "user_reports": [], "id": "dgbl2dm", "gilded": 0, "archived": false, "score": 1, "report_reasons": null, "author": "ThatPhoneGuy", "parent_id": "t3_65lkfr", "subreddit_name_prefixed": "r/guns", "controversiality": 0, "body": "Impressive! ", "edited": false, "downs": 0, "body_html": "&lt;div class=\"md\"&gt;&lt;p&gt;Impressive! &lt;/p&gt;\n&lt;/div&gt;", "subreddit": "guns", "name": "t1_dgbl2dm", "score_hidden": false, "stickied": false, "created": 1492340271.0, "created_utc": 1492311471.0, "depth": 0, "mod_reports": [], "subreddit_type": "public", "ups": 1}}, {"kind": "t1", "data": {"subreddit_id": "t5_2qhc8", "removal_reason": null, "link_id": "t3_65lkfr", "likes": null, "replies": "", "user_reports": [], "id": "dgbmv2a", "gilded": 0, "archived": false, "score": 1, "report_reasons": null, "author": "vZeppelin", "parent_id": "t3_65lkfr", "subreddit_name_prefixed": "r/guns", "controversiality": 0, "body": "god dam I want a SCAR 16 so bad. I really think it'll be my next long gun. Just as long as no crazy deals fall into my lap.", "edited": false, "downs": 0, "body_html": "&lt;div class=\"md\"&gt;&lt;p&gt;god dam I want a SCAR 16 so bad. I really think it&amp;#39;ll be my next long gun. Just as long as no crazy deals fall into my lap.&lt;/p&gt;\n&lt;/div&gt;", "subreddit": "guns", "name": "t1_dgbmv2a", "score_hidden": false, "stickied": false, "created": 1492342994.0, "created_utc": 1492314194.0, "depth": 0, "mod_reports": [], "subreddit_type": "public", "ups": 1}}, {"kind": "t1", "data": {"subreddit_id": "t5_2qhc8", "removal_reason": null, "link_id": "t3_65lkfr", "likes": null, "replies": "", "user_reports": [], "id": "dgbog20", "gilded": 0, "archived": false, "score": 1, "report_reasons": null, "author": "oompahlumpa", "parent_id": "t3_65lkfr", "subreddit_name_prefixed": "r/guns", "controversiality": 0, "body": "Damn you have a bad ass collection!", "edited": false, "downs": 0, "body_html": "&lt;div class=\"md\"&gt;&lt;p&gt;Damn you have a bad ass collection!&lt;/p&gt;\n&lt;/div&gt;", "subreddit": "guns", "name": "t1_dgbog20", "score_hidden": false, "stickied": false, "created": 1492345638.0, "created_utc": 1492316838.0, "depth": 0, "mod_reports": [], "subreddit_type": "public", "ups": 1}}, {"kind": "t1", "data": {"subreddit_id": "t5_2qhc8", "removal_reason": null, "link_id": "t3_65lkfr", "likes": null, "replies": {"kind": "Listing", "data": {"modhash": "", "children": [{"kind": "t1", "data": {"subreddit_id": "t5_2qhc8", "removal_reason": null, "link_id": "t3_65lkfr", "likes": null, "replies": "", "user_reports": [], "id": "dgbovc5", "gilded": 0, "archived": false, "score": 1, "report_reasons": null, "author": "fat_italian_stallion", "parent_id": "t1_dgborsi", "subreddit_name_prefixed": "r/guns", "controversiality": 0, "body": "Larue index clips", "edited": false, "downs": 0, "body_html": "&lt;div class=\"md\"&gt;&lt;p&gt;Larue index clips&lt;/p&gt;\n&lt;/div&gt;", "subreddit": "guns", "name": "t1_dgbovc5", "score_hidden": false, "stickied": false, "created": 1492346369.0, "created_utc": 1492317569.0, "depth": 1, "mod_reports": [], "subreddit_type": "public", "ups": 1}}], "after": null, "before": null}}, "user_reports": [], "id": "dgborsi", "gilded": 0, "archived": false, "score": 1, "report_reasons": null, "author": "[deleted]", "parent_id": "t3_65lkfr", "subreddit_name_prefixed": "r/guns", "controversiality": 0, "body": "[deleted]", "edited": false, "downs": 0, "body_html": "&lt;div class=\"md\"&gt;&lt;p&gt;[deleted]&lt;/p&gt;\n&lt;/div&gt;", "subreddit": "guns", "name": "t1_dgborsi", "score_hidden": false, "stickied": false, "created": 1492346196.0, "created_utc": 1492317396.0, "depth": 0, "mod_reports": [], "subreddit_type": "public", "ups": 1}}, {"kind": "t1", "data": {"subreddit_id": "t5_2qhc8", "removal_reason": null, "link_id": "t3_65lkfr", "likes": null, "replies": "", "user_reports": [], "id": "dgbrenc", "gilded": 0, "archived": false, "score": 1, "report_reasons": null, "author": "JMS144", "parent_id": "t3_65lkfr", "subreddit_name_prefixed": "r/guns", "controversiality": 0, "body": "I shall live by this. Thank you, mentor ", "edited": false, "downs": 0, "body_html": "&lt;div class=\"md\"&gt;&lt;p&gt;I shall live by this. Thank you, mentor &lt;/p&gt;\n&lt;/div&gt;", "subreddit": "guns", "name": "t1_dgbrenc", "score_hidden": false, "stickied": false, "created": 1492351317.0, "created_utc": 1492322517.0, "depth": 0, "mod_reports": [], "subreddit_type": "public", "ups": 1}}, {"kind": "t1", "data": {"subreddit_id": "t5_2qhc8", "removal_reason": null, "link_id": "t3_65lkfr", "likes": null, "replies": "", "user_reports": [], "id": "dgbsszn", "gilded": 0, "archived": false, "score": 1, "report_reasons": null, "author": "Swerverdude", "parent_id": "t3_65lkfr", "subreddit_name_prefixed": "r/guns", "controversiality": 0, "body": "You are living in my dreams", "edited": false, "downs": 0, "body_html": "&lt;div class=\"md\"&gt;&lt;p&gt;You are living in my dreams&lt;/p&gt;\n&lt;/div&gt;", "subreddit": "guns", "name": "t1_dgbsszn", "score_hidden": false, "stickied": false, "created": 1492354737.0, "created_utc": 1492325937.0, "depth": 0, "mod_reports": [], "subreddit_type": "public", "ups": 1}}, {"kind": "t1", "data": {"subreddit_id": "t5_2qhc8", "removal_reason": null, "link_id": "t3_65lkfr", "likes": null, "replies": "", "user_reports": [], "id": "dgbtk4c", "gilded": 0, "archived": false, "score": 1, "report_reasons": null, "author": "ledzep4life", "parent_id": "t3_65lkfr", "subreddit_name_prefixed": "r/guns", "controversiality": 0, "body": "gib", "edited": false, "downs": 0, "body_html": "&lt;div class=\"md\"&gt;&lt;p&gt;gib&lt;/p&gt;\n&lt;/div&gt;", "subreddit": "guns", "name": "t1_dgbtk4c", "score_hidden": false, "stickied": false, "created": 1492356783.0, "created_utc": 1492327983.0, "depth": 0, "mod_reports": [], "subreddit_type": "public", "ups": 1}}, {"kind": "t1", "data": {"subreddit_id": "t5_2qhc8", "removal_reason": null, "link_id": "t3_65lkfr", "likes": null, "replies": {"kind": "Listing", "data": {"modhash": "", "children": [{"kind": "t1", "data": {"subreddit_id": "t5_2qhc8", "removal_reason": null, "link_id": "t3_65lkfr", "likes": null, "replies": "", "user_reports": [], "id": "dgca2i8", "gilded": 0, "archived": false, "score": 1, "report_reasons": null, "author": "fat_italian_stallion", "parent_id": "t1_dgc8x40", "subreddit_name_prefixed": "r/guns", "controversiality": 0, "body": "Never had an issue with them. I run those and the PSA D&amp;H mags. No complaints. ", "edited": false, "downs": 0, "body_html": "&lt;div class=\"md\"&gt;&lt;p&gt;Never had an issue with them. I run those and the PSA D&amp;amp;H mags. No complaints. &lt;/p&gt;\n&lt;/div&gt;", "subreddit": "guns", "name": "t1_dgca2i8", "score_hidden": false, "stickied": false, "created": 1492391534.0, "created_utc": 1492362734.0, "depth": 1, "mod_reports": [], "subreddit_type": "public", "ups": 1}}], "after": null, "before": null}}, "user_reports": [], "id": "dgc8x40", "gilded": 0, "archived": false, "score": 1, "report_reasons": null, "author": "JeffNasty", "parent_id": "t3_65lkfr", "subreddit_name_prefixed": "r/guns", "controversiality": 0, "body": "How are you liking Lancer5AWM's in the Scar?  Do they work well and if you seat them rather violently do they shoot a round out of the feed lips?", "edited": false, "downs": 0, "body_html": "&lt;div class=\"md\"&gt;&lt;p&gt;How are you liking Lancer5AWM&amp;#39;s in the Scar?  Do they work well and if you seat them rather violently do they shoot a round out of the feed lips?&lt;/p&gt;\n&lt;/div&gt;", "subreddit": "guns", "name": "t1_dgc8x40", "score_hidden": false, "stickied": false, "created": 1492390057.0, "created_utc": 1492361257.0, "depth": 0, "mod_reports": [], "subreddit_type": "public", "ups": 1}}, {"kind": "t1", "data": {"subreddit_id": "t5_2qhc8", "removal_reason": null, "link_id": "t3_65lkfr", "likes": null, "replies": {"kind": "Listing", "data": {"modhash": "", "children": [{"kind": "t1", "data": {"subreddit_id": "t5_2qhc8", "removal_reason": null, "link_id": "t3_65lkfr", "likes": null, "replies": {"kind": "Listing", "data": {"modhash": "", "children": [{"kind": "t1", "data": {"subreddit_id": "t5_2qhc8", "removal_reason": null, "link_id": "t3_65lkfr", "likes": null, "replies": "", "user_reports": [], "id": "dgclg4c", "gilded": 0, "archived": false, "score": 1, "report_reasons": null, "author": "rpowsm86", "parent_id": "t1_dgcfoep", "subreddit_name_prefixed": "r/guns", "controversiality": 0, "body": "Figured the cartridges just too lazy to google lol nice collections", "edited": false, "downs": 0, "body_html": "&lt;div class=\"md\"&gt;&lt;p&gt;Figured the cartridges just too lazy to google lol nice collections&lt;/p&gt;\n&lt;/div&gt;", "subreddit": "guns", "name": "t1_dgclg4c", "score_hidden": false, "stickied": false, "created": 1492406488.0, "created_utc": 1492377688.0, "depth": 2, "mod_reports": [], "subreddit_type": "public", "ups": 1}}], "after": null, "before": null}}, "user_reports": [], "id": "dgcfoep", "gilded": 0, "archived": false, "score": 1, "report_reasons": null, "author": "fat_italian_stallion", "parent_id": "t1_dgcckw2", "subreddit_name_prefixed": "r/guns", "controversiality": 0, "body": "cartridge and size", "edited": false, "downs": 0, "body_html": "&lt;div class=\"md\"&gt;&lt;p&gt;cartridge and size&lt;/p&gt;\n&lt;/div&gt;", "subreddit": "guns", "name": "t1_dgcfoep", "score_hidden": false, "stickied": false, "created": 1492398989.0, "created_utc": 1492370189.0, "depth": 1, "mod_reports": [], "subreddit_type": "public", "ups": 1}}], "after": null, "before": null}}, "user_reports": [], "id": "dgcckw2", "gilded": 0, "archived": false, "score": 1, "report_reasons": null, "author": "rpowsm86", "parent_id": "t3_65lkfr", "subreddit_name_prefixed": "r/guns", "controversiality": 0, "body": "Whats the difference between a 16 &amp; a 17?", "edited": false, "downs": 0, "body_html": "&lt;div class=\"md\"&gt;&lt;p&gt;Whats the difference between a 16 &amp;amp; a 17?&lt;/p&gt;\n&lt;/div&gt;", "subreddit": "guns", "name": "t1_dgcckw2", "score_hidden": false, "stickied": false, "created": 1492394842.0, "created_utc": 1492366042.0, "depth": 0, "mod_reports": [], "subreddit_type": "public", "ups": 1}}, {"kind": "t1", "data": {"subreddit_id": "t5_2qhc8", "removal_reason": null, "link_id": "t3_65lkfr", "likes": null, "replies": "", "user_reports": [], "id": "dgck4ud", "gilded": 0, "archived": false, "score": 1, "report_reasons": null, "author": "WutAnIntern", "parent_id": "t3_65lkfr", "subreddit_name_prefixed": "r/guns", "controversiality": 0, "body": "DK if OP likes guns or hates money more. I'm peanut butter and jealous. ", "edited": false, "downs": 0, "body_html": "&lt;div class=\"md\"&gt;&lt;p&gt;DK if OP likes guns or hates money more. I&amp;#39;m peanut butter and jealous. &lt;/p&gt;\n&lt;/div&gt;", "subreddit": "guns", "name": "t1_dgck4ud", "score_hidden": false, "stickied": false, "created": 1492404766.0, "created_utc": 1492375966.0, "depth": 0, "mod_reports": [], "subreddit_type": "public", "ups": 1}}, {"kind": "t1", "data": {"subreddit_id": "t5_2qhc8", "removal_reason": null, "link_id": "t3_65lkfr", "likes": null, "replies": "", "user_reports": [], "id": "dgbdw60", "gilded": 0, "archived": false, "score": 1, "report_reasons": null, "author": "Hobewan", "parent_id": "t3_65lkfr", "subreddit_name_prefixed": "r/guns", "controversiality": 0, "body": "\"Some sort of Saturday alliteration\" would have been better.", "edited": false, "downs": 0, "body_html": "&lt;div class=\"md\"&gt;&lt;p&gt;&amp;quot;Some sort of Saturday alliteration&amp;quot; would have been better.&lt;/p&gt;\n&lt;/div&gt;", "subreddit": "guns", "name": "t1_dgbdw60", "score_hidden": false, "stickied": false, "created": 1492329855.0, "created_utc": 1492301055.0, "depth": 0, "mod_reports": [], "subreddit_type": "public", "ups": 1}}, {"kind": "t1", "data": {"subreddit_id": "t5_2qhc8", "removal_reason": null, "link_id": "t3_65lkfr", "likes": null, "replies": {"kind": "Listing", "data": {"modhash": "", "children": [{"kind": "t1", "data": {"subreddit_id": "t5_2qhc8", "removal_reason": null, "link_id": "t3_65lkfr", "likes": null, "replies": {"kind": "Listing", "data": {"modhash": "", "children": [{"kind": "t1", "data": {"subreddit_id": "t5_2qhc8", "removal_reason": null, "link_id": "t3_65lkfr", "likes": null, "replies": {"kind": "Listing", "data": {"modhash": "", "children": [{"kind": "t1", "data": {"subreddit_id": "t5_2qhc8", "removal_reason": null, "link_id": "t3_65lkfr", "likes": null, "replies": "", "user_reports": [], "id": "dgbfo8d", "gilded": 0, "archived": false, "score": 2, "report_reasons": null, "author": "fat_italian_stallion", "parent_id": "t1_dgbeo9y", "subreddit_name_prefixed": "r/guns", "controversiality": 0, "body": "Gracias for link", "edited": false, "downs": 0, "body_html": "&lt;div class=\"md\"&gt;&lt;p&gt;Gracias for link&lt;/p&gt;\n&lt;/div&gt;", "subreddit": "guns", "name": "t1_dgbfo8d", "score_hidden": false, "stickied": false, "created": 1492332437.0, "created_utc": 1492303637.0, "depth": 3, "mod_reports": [], "subreddit_type": "public", "ups": 2}}], "after": null, "before": null}}, "user_reports": [], "id": "dgbeo9y", "gilded": 0, "archived": false, "score": 5, "report_reasons": null, "author": "_2na", "parent_id": "t1_dgbe8kw", "subreddit_name_prefixed": "r/guns", "controversiality": 0, "body": "[Summit Gun Broker](http://summitgunbroker.com/elcan-m145.html) has them for $469", "edited": false, "downs": 0, "body_html": "&lt;div class=\"md\"&gt;&lt;p&gt;&lt;a href=\"http://summitgunbroker.com/elcan-m145.html\"&gt;Summit Gun Broker&lt;/a&gt; has them for $469&lt;/p&gt;\n&lt;/div&gt;", "subreddit": "guns", "name": "t1_dgbeo9y", "score_hidden": false, "stickied": false, "created": 1492330994.0, "created_utc": 1492302194.0, "depth": 2, "mod_reports": [], "subreddit_type": "public", "ups": 5}}], "after": null, "before": null}}, "user_reports": [], "id": "dgbe8kw", "gilded": 0, "archived": false, "score": 2, "report_reasons": null, "author": "fat_italian_stallion", "parent_id": "t1_dgbe6k7", "subreddit_name_prefixed": "r/guns", "controversiality": 0, "body": "Possibly part of the plan, or an acog mgo", "edited": false, "downs": 0, "body_html": "&lt;div class=\"md\"&gt;&lt;p&gt;Possibly part of the plan, or an acog mgo&lt;/p&gt;\n&lt;/div&gt;", "subreddit": "guns", "name": "t1_dgbe8kw", "score_hidden": false, "stickied": false, "created": 1492330353.0, "created_utc": 1492301553.0, "depth": 1, "mod_reports": [], "subreddit_type": "public", "ups": 2}}], "after": null, "before": null}}, "user_reports": [], "id": "dgbe6k7", "gilded": 0, "archived": false, "score": 1, "report_reasons": null, "author": "Hesalite", "parent_id": "t3_65lkfr", "subreddit_name_prefixed": "r/guns", "controversiality": 0, "body": "That saw would look awesome with an M145", "edited": false, "downs": 0, "body_html": "&lt;div class=\"md\"&gt;&lt;p&gt;That saw would look awesome with an M145&lt;/p&gt;\n&lt;/div&gt;", "subreddit": "guns", "name": "t1_dgbe6k7", "score_hidden": false, "stickied": false, "created": 1492330270.0, "created_utc": 1492301470.0, "depth": 0, "mod_reports": [], "subreddit_type": "public", "ups": 1}}, {"kind": "t1", "data": {"subreddit_id": "t5_2qhc8", "removal_reason": null, "link_id": "t3_65lkfr", "likes": null, "replies": {"kind": "Listing", "data": {"modhash": "", "children": [{"kind": "t1", "data": {"subreddit_id": "t5_2qhc8", "removal_reason": null, "link_id": "t3_65lkfr", "likes": null, "replies": "", "user_reports": [], "id": "dgd48gr", "gilded": 0, "archived": false, "score": 0, "report_reasons": null, "author": "1234fakestreets", "parent_id": "t1_dgd47ul", "subreddit_name_prefixed": "r/guns", "controversiality": 0, "body": "Wait, you have a safe in your kitchen?", "edited": false, "downs": 0, "body_html": "&lt;div class=\"md\"&gt;&lt;p&gt;Wait, you have a safe in your kitchen?&lt;/p&gt;\n&lt;/div&gt;", "subreddit": "guns", "name": "t1_dgd48gr", "score_hidden": false, "stickied": false, "created": 1492432688.0, "created_utc": 1492403888.0, "depth": 1, "mod_reports": [], "subreddit_type": "public", "ups": 0}}], "after": null, "before": null}}, "user_reports": [], "id": "dgd47ul", "gilded": 0, "archived": false, "score": 0, "report_reasons": null, "author": "1234fakestreets", "parent_id": "t3_65lkfr", "subreddit_name_prefixed": "r/guns", "controversiality": 0, "body": "You use your oven as a photo booth or something?", "edited": false, "downs": 0, "body_html": "&lt;div class=\"md\"&gt;&lt;p&gt;You use your oven as a photo booth or something?&lt;/p&gt;\n&lt;/div&gt;", "subreddit": "guns", "name": "t1_dgd47ul", "score_hidden": false, "stickied": false, "created": 1492432656.0, "created_utc": 1492403856.0, "depth": 0, "mod_reports": [], "subreddit_type": "public", "ups": 0}}, {"kind": "t1", "data": {"subreddit_id": "t5_2qhc8", "removal_reason": null, "link_id": "t3_65lkfr", "likes": null, "replies": "", "user_reports": [], "id": "dgbuxsl", "gilded": 0, "archived": false, "score": -2, "report_reasons": null, "author": "LoneMarauder55", "parent_id": "t3_65lkfr", "subreddit_name_prefixed": "r/guns", "controversiality": 0, "body": "http://getyarn.io/yarn-clip/d58071b4-164b-4f41-83ae-32eca806b09b", "edited": false, "downs": 0, "body_html": "&lt;div class=\"md\"&gt;&lt;p&gt;&lt;a href=\"http://getyarn.io/yarn-clip/d58071b4-164b-4f41-83ae-32eca806b09b\"&gt;http://getyarn.io/yarn-clip/d58071b4-164b-4f41-83ae-32eca806b09b&lt;/a&gt;&lt;/p&gt;\n&lt;/div&gt;", "subreddit": "guns", "name": "t1_dgbuxsl", "score_hidden": false, "stickied": false, "created": 1492361043.0, "created_utc": 1492332243.0, "depth": 0, "mod_reports": [], "subreddit_type": "public", "ups": -2}}], "after": null, "before": null}}]