[{"kind": "Listing", "data": {"modhash": "", "children": [{"kind": "t3", "data": {"contest_mode": false, "banned_by": null, "media_embed": {}, "subreddit": "starterpacks", "selftext_html": null, "selftext": "", "likes": null, "suggested_sort": null, "user_reports": [], "secure_media": null, "link_flair_text": null, "id": "64u57t", "gilded": 0, "secure_media_embed": {}, "clicked": false, "score": 142, "report_reasons": null, "author": "HolUp3", "saved": false, "mod_reports": [], "name": "t3_64u57t", "subreddit_name_prefixed": "r/starterpacks", "approved_by": null, "over_18": false, "domain": "i.imgur.com", "hidden": false, "preview": {"images": [{"source": {"url": "https://i.redditmedia.com/wQfaZQouBSfQlyNwL-CKm9Um6hkXt-Pi2W_gkz6jdiU.png?s=ccd32fd18f55fefd020710ba513292fd", "width": 799, "height": 600}, "resolutions": [{"url": "https://i.redditmedia.com/wQfaZQouBSfQlyNwL-CKm9Um6hkXt-Pi2W_gkz6jdiU.png?fit=crop&amp;crop=faces%2Centropy&amp;arh=2&amp;w=108&amp;s=377496555653afa0bd9d5378e07408eb", "width": 108, "height": 81}, {"url": "https://i.redditmedia.com/wQfaZQouBSfQlyNwL-CKm9Um6hkXt-Pi2W_gkz6jdiU.png?fit=crop&amp;crop=faces%2Centropy&amp;arh=2&amp;w=216&amp;s=38746b8ea6f33fb67eafb54b094e00b0", "width": 216, "height": 162}, {"url": "https://i.redditmedia.com/wQfaZQouBSfQlyNwL-CKm9Um6hkXt-Pi2W_gkz6jdiU.png?fit=crop&amp;crop=faces%2Centropy&amp;arh=2&amp;w=320&amp;s=f8193c49ee0457207774e6122943e067", "width": 320, "height": 240}, {"url": "https://i.redditmedia.com/wQfaZQouBSfQlyNwL-CKm9Um6hkXt-Pi2W_gkz6jdiU.png?fit=crop&amp;crop=faces%2Centropy&amp;arh=2&amp;w=640&amp;s=aab651bb0915ac9b6f0c76544cb80f4f", "width": 640, "height": 480}], "variants": {}, "id": "6SxmrDEiJbdYyOaWryLSSqL7WOeXPiAXxHta3QgCFZM"}], "enabled": true}, "thumbnail": "https://b.thumbs.redditmedia.com/VJc5kD07JZ7mLDsR2M2tR3mOq4Hm-NMDElWeUS2S2SM.jpg", "subreddit_id": "t5_34o9s", "edited": false, "link_flair_css_class": null, "author_flair_css_class": null, "downs": 0, "brand_safe": true, "archived": false, "removal_reason": null, "post_hint": "image", "is_self": false, "hide_score": false, "spoiler": false, "permalink": "/r/starterpacks/comments/64u57t/late_2000s_kid_starter_pack/", "num_reports": null, "locked": false, "stickied": false, "created": 1491977771.0, "url": "http://i.imgur.com/YvFxE2i.png", "author_flair_text": null, "quarantine": false, "title": "Late 2000s kid starter pack", "created_utc": 1491948971.0, "distinguished": null, "media": null, "upvote_ratio": 0.84, "num_comments": 20, "visited": false, "subreddit_type": "public", "ups": 142}}], "after": null, "before": null}}, {"kind": "Listing", "data": {"modhash": "", "children": [{"kind": "t1", "data": {"subreddit_id": "t5_34o9s", "removal_reason": null, "link_id": "t3_64u57t", "likes": null, "replies": {"kind": "Listing", "data": {"modhash": "", "children": [{"kind": "t1", "data": {"subreddit_id": "t5_34o9s", "removal_reason": null, "link_id": "t3_64u57t", "likes": null, "replies": "", "user_reports": [], "id": "dg5b2bq", "gilded": 0, "archived": false, "score": 45, "report_reasons": null, "author": "mathisawsome2213", "parent_id": "t1_dg53n5a", "subreddit_name_prefixed": "r/starterpacks", "controversiality": 0, "body": "No kidding. Why is Ratatouille even on there? Why is Dark Knight on there? Because they came out in that general time period?\n\n0/10 pack", "edited": false, "downs": 0, "body_html": "&lt;div class=\"md\"&gt;&lt;p&gt;No kidding. Why is Ratatouille even on there? Why is Dark Knight on there? Because they came out in that general time period?&lt;/p&gt;\n\n&lt;p&gt;0/10 pack&lt;/p&gt;\n&lt;/div&gt;", "subreddit": "starterpacks", "name": "t1_dg5b2bq", "score_hidden": false, "stickied": false, "created": 1491991383.0, "created_utc": 1491962583.0, "depth": 1, "mod_reports": [], "subreddit_type": "public", "ups": 45}}], "after": null, "before": null}}, "user_reports": [], "id": "dg53n5a", "gilded": 0, "archived": false, "score": 76, "report_reasons": null, "author": "hazpat", "parent_id": "t3_64u57t", "subreddit_name_prefixed": "r/starterpacks", "controversiality": 0, "body": "this is too bland. like the vanilla of starter packs.", "edited": false, "downs": 0, "body_html": "&lt;div class=\"md\"&gt;&lt;p&gt;this is too bland. like the vanilla of starter packs.&lt;/p&gt;\n&lt;/div&gt;", "subreddit": "starterpacks", "name": "t1_dg53n5a", "score_hidden": false, "stickied": false, "created": 1491981584.0, "created_utc": 1491952784.0, "depth": 0, "mod_reports": [], "subreddit_type": "public", "ups": 76}}, {"kind": "t1", "data": {"subreddit_id": "t5_34o9s", "removal_reason": null, "link_id": "t3_64u57t", "likes": null, "replies": {"kind": "Listing", "data": {"modhash": "", "children": [{"kind": "t1", "data": {"subreddit_id": "t5_34o9s", "removal_reason": null, "link_id": "t3_64u57t", "likes": null, "replies": "", "user_reports": [], "id": "dg535uf", "gilded": 0, "archived": false, "score": 10, "report_reasons": null, "author": "HolUp3", "parent_id": "t1_dg5339l", "subreddit_name_prefixed": "r/starterpacks", "controversiality": 0, "body": "If you turned 6 in a time period, you're a \"kid\" of that time period, imo. It's not necessarily about when you were born.\n\nSo, someone born in 2001 would be a late 2000s kid, because they mostly have childhood memories of 2007-2011.", "edited": false, "downs": 0, "body_html": "&lt;div class=\"md\"&gt;&lt;p&gt;If you turned 6 in a time period, you&amp;#39;re a &amp;quot;kid&amp;quot; of that time period, imo. It&amp;#39;s not necessarily about when you were born.&lt;/p&gt;\n\n&lt;p&gt;So, someone born in 2001 would be a late 2000s kid, because they mostly have childhood memories of 2007-2011.&lt;/p&gt;\n&lt;/div&gt;", "subreddit": "starterpacks", "name": "t1_dg535uf", "score_hidden": false, "stickied": false, "created": 1491980924.0, "created_utc": 1491952124.0, "depth": 1, "mod_reports": [], "subreddit_type": "public", "ups": 10}}], "after": null, "before": null}}, "user_reports": [], "id": "dg5339l", "gilded": 0, "archived": false, "score": 35, "report_reasons": null, "author": "thatsoreddit", "parent_id": "t3_64u57t", "subreddit_name_prefixed": "r/starterpacks", "controversiality": 0, "body": "Nononono, you seem to have confused \"early 2000s kid\" and \"mid 2000s\" kid. Two completely separate breeds.", "edited": false, "downs": 0, "body_html": "&lt;div class=\"md\"&gt;&lt;p&gt;Nononono, you seem to have confused &amp;quot;early 2000s kid&amp;quot; and &amp;quot;mid 2000s&amp;quot; kid. Two completely separate breeds.&lt;/p&gt;\n&lt;/div&gt;", "subreddit": "starterpacks", "name": "t1_dg5339l", "score_hidden": false, "stickied": false, "created": 1491980826.0, "created_utc": 1491952026.0, "depth": 0, "mod_reports": [], "subreddit_type": "public", "ups": 35}}, {"kind": "t1", "data": {"subreddit_id": "t5_34o9s", "removal_reason": null, "link_id": "t3_64u57t", "likes": null, "replies": {"kind": "Listing", "data": {"modhash": "", "children": [{"kind": "t1", "data": {"subreddit_id": "t5_34o9s", "removal_reason": null, "link_id": "t3_64u57t", "likes": null, "replies": "", "user_reports": [], "id": "dg6vm8f", "gilded": 0, "archived": false, "score": 4, "report_reasons": null, "author": "The_Fool-On-The_Hill", "parent_id": "t1_dg6s15a", "subreddit_name_prefixed": "r/starterpacks", "controversiality": 0, "body": "I do, it was just shit", "edited": false, "downs": 0, "body_html": "&lt;div class=\"md\"&gt;&lt;p&gt;I do, it was just shit&lt;/p&gt;\n&lt;/div&gt;", "subreddit": "starterpacks", "name": "t1_dg6vm8f", "score_hidden": false, "stickied": false, "created": 1492073802.0, "created_utc": 1492045002.0, "depth": 1, "mod_reports": [], "subreddit_type": "public", "ups": 4}}, {"kind": "t1", "data": {"subreddit_id": "t5_34o9s", "removal_reason": null, "link_id": "t3_64u57t", "likes": null, "replies": "", "user_reports": [], "id": "dg8qipt", "gilded": 0, "archived": false, "score": 1, "report_reasons": null, "author": "theskepticalsquid", "parent_id": "t1_dg6s15a", "subreddit_name_prefixed": "r/starterpacks", "controversiality": 0, "body": "I was born in 99, when I was in junior high we had to watch it for English class. Don't remember why but I never cared for it ", "edited": false, "downs": 0, "body_html": "&lt;div class=\"md\"&gt;&lt;p&gt;I was born in 99, when I was in junior high we had to watch it for English class. Don&amp;#39;t remember why but I never cared for it &lt;/p&gt;\n&lt;/div&gt;", "subreddit": "starterpacks", "name": "t1_dg8qipt", "score_hidden": false, "stickied": false, "created": 1492171608.0, "created_utc": 1492142808.0, "depth": 1, "mod_reports": [], "subreddit_type": "public", "ups": 1}}], "after": null, "before": null}}, "user_reports": [], "id": "dg6s15a", "gilded": 0, "archived": false, "score": 12, "report_reasons": null, "author": "Marsmar-LordofMars", "parent_id": "t3_64u57t", "subreddit_name_prefixed": "r/starterpacks", "controversiality": 0, "body": "Do 2000s kids even remember Avatar? That film had 0 cultural impact. ", "edited": false, "downs": 0, "body_html": "&lt;div class=\"md\"&gt;&lt;p&gt;Do 2000s kids even remember Avatar? That film had 0 cultural impact. &lt;/p&gt;\n&lt;/div&gt;", "subreddit": "starterpacks", "name": "t1_dg6s15a", "score_hidden": false, "stickied": false, "created": 1492069449.0, "created_utc": 1492040649.0, "depth": 0, "mod_reports": [], "subreddit_type": "public", "ups": 12}}, {"kind": "t1", "data": {"subreddit_id": "t5_34o9s", "removal_reason": null, "link_id": "t3_64u57t", "likes": null, "replies": {"kind": "Listing", "data": {"modhash": "", "children": [{"kind": "t1", "data": {"subreddit_id": "t5_34o9s", "removal_reason": null, "link_id": "t3_64u57t", "likes": null, "replies": {"kind": "Listing", "data": {"modhash": "", "children": [{"kind": "t1", "data": {"subreddit_id": "t5_34o9s", "removal_reason": null, "link_id": "t3_64u57t", "likes": null, "replies": {"kind": "Listing", "data": {"modhash": "", "children": [{"kind": "t1", "data": {"subreddit_id": "t5_34o9s", "removal_reason": null, "link_id": "t3_64u57t", "likes": null, "replies": "", "user_reports": [], "id": "dg6otn6", "gilded": 0, "archived": false, "score": 4, "report_reasons": null, "author": "T0Mjefferson", "parent_id": "t1_dg5rw9l", "subreddit_name_prefixed": "r/starterpacks", "controversiality": 0, "body": "o say does that sponge-spangled banner yet waaave", "edited": false, "downs": 0, "body_html": "&lt;div class=\"md\"&gt;&lt;p&gt;o say does that sponge-spangled banner yet waaave&lt;/p&gt;\n&lt;/div&gt;", "subreddit": "starterpacks", "name": "t1_dg6otn6", "score_hidden": false, "stickied": false, "created": 1492065494.0, "created_utc": 1492036694.0, "depth": 3, "mod_reports": [], "subreddit_type": "public", "ups": 4}}], "after": null, "before": null}}, "user_reports": [], "id": "dg5rw9l", "gilded": 0, "archived": false, "score": 2, "report_reasons": null, "author": "SeanTheTranslator", "parent_id": "t1_dg5h4dr", "subreddit_name_prefixed": "r/starterpacks", "controversiality": 0, "body": "It was still there", "edited": false, "downs": 0, "body_html": "&lt;div class=\"md\"&gt;&lt;p&gt;It was still there&lt;/p&gt;\n&lt;/div&gt;", "subreddit": "starterpacks", "name": "t1_dg5rw9l", "score_hidden": false, "stickied": false, "created": 1492027835.0, "created_utc": 1491999035.0, "depth": 2, "mod_reports": [], "subreddit_type": "public", "ups": 2}}, {"kind": "t1", "data": {"subreddit_id": "t5_34o9s", "removal_reason": null, "link_id": "t3_64u57t", "likes": null, "replies": "", "user_reports": [], "id": "dg63o1e", "gilded": 0, "archived": false, "score": 2, "report_reasons": null, "author": "BaconLondoner", "parent_id": "t1_dg5h4dr", "subreddit_name_prefixed": "r/starterpacks", "controversiality": 0, "body": "Kids still watched it", "edited": false, "downs": 0, "body_html": "&lt;div class=\"md\"&gt;&lt;p&gt;Kids still watched it&lt;/p&gt;\n&lt;/div&gt;", "subreddit": "starterpacks", "name": "t1_dg63o1e", "score_hidden": false, "stickied": false, "created": 1492042880.0, "created_utc": 1492014080.0, "depth": 2, "mod_reports": [], "subreddit_type": "public", "ups": 2}}, {"kind": "t1", "data": {"subreddit_id": "t5_34o9s", "removal_reason": null, "link_id": "t3_64u57t", "likes": null, "replies": "", "user_reports": [], "id": "dg8iih7", "gilded": 0, "archived": false, "score": 2, "report_reasons": null, "author": "PM_ME_CARTOON_PICS", "parent_id": "t1_dg5h4dr", "subreddit_name_prefixed": "r/starterpacks", "controversiality": 0, "body": "ye but all the kids loved it\n\nsource: am kid", "edited": false, "downs": 0, "body_html": "&lt;div class=\"md\"&gt;&lt;p&gt;ye but all the kids loved it&lt;/p&gt;\n\n&lt;p&gt;source: am kid&lt;/p&gt;\n&lt;/div&gt;", "subreddit": "starterpacks", "name": "t1_dg8iih7", "score_hidden": false, "stickied": false, "created": 1492159944.0, "created_utc": 1492131144.0, "depth": 2, "mod_reports": [], "subreddit_type": "public", "ups": 2}}], "after": null, "before": null}}, "user_reports": [], "id": "dg5h4dr", "gilded": 0, "archived": false, "score": -1, "report_reasons": null, "author": "HolUp3", "parent_id": "t1_dg5fz05", "subreddit_name_prefixed": "r/starterpacks", "controversiality": 0, "body": "Spongebob was terrible by 2007", "edited": false, "downs": 0, "body_html": "&lt;div class=\"md\"&gt;&lt;p&gt;Spongebob was terrible by 2007&lt;/p&gt;\n&lt;/div&gt;", "subreddit": "starterpacks", "name": "t1_dg5h4dr", "score_hidden": false, "stickied": false, "created": 1492000490.0, "created_utc": 1491971690.0, "depth": 1, "mod_reports": [], "subreddit_type": "public", "ups": -1}}], "after": null, "before": null}}, "user_reports": [], "id": "dg5fz05", "gilded": 0, "archived": false, "score": 7, "report_reasons": null, "author": "AwesomeSaucer9", "parent_id": "t3_64u57t", "subreddit_name_prefixed": "r/starterpacks", "controversiality": 0, "body": "Replace Hannah Montana with Spongebob Squarepants.\n\nAnd then it's perfect.", "edited": false, "downs": 0, "body_html": "&lt;div class=\"md\"&gt;&lt;p&gt;Replace Hannah Montana with Spongebob Squarepants.&lt;/p&gt;\n\n&lt;p&gt;And then it&amp;#39;s perfect.&lt;/p&gt;\n&lt;/div&gt;", "subreddit": "starterpacks", "name": "t1_dg5fz05", "score_hidden": false, "stickied": false, "created": 1491998515.0, "created_utc": 1491969715.0, "depth": 0, "mod_reports": [], "subreddit_type": "public", "ups": 7}}, {"kind": "t1", "data": {"subreddit_id": "t5_34o9s", "removal_reason": null, "link_id": "t3_64u57t", "likes": null, "replies": "", "user_reports": [], "id": "dg51h20", "gilded": 0, "archived": false, "score": 7, "report_reasons": null, "author": "HolUp3", "parent_id": "t3_64u57t", "subreddit_name_prefixed": "r/starterpacks", "controversiality": 0, "body": "inb4 \"The Dark Knight isn't a kids movie\"\n\nTrue, it's not, but I remember it being rather popular among kids, teens, and adults all at once. Sure it has violent/adult moments, but Back to the Future was loved by kids and it had \"adult\" moments too (like Doc Brown being gunned down, Biff assaulting Marty's mom, or the occasional mild swears).", "edited": false, "downs": 0, "body_html": "&lt;div class=\"md\"&gt;&lt;p&gt;inb4 &amp;quot;The Dark Knight isn&amp;#39;t a kids movie&amp;quot;&lt;/p&gt;\n\n&lt;p&gt;True, it&amp;#39;s not, but I remember it being rather popular among kids, teens, and adults all at once. Sure it has violent/adult moments, but Back to the Future was loved by kids and it had &amp;quot;adult&amp;quot; moments too (like Doc Brown being gunned down, Biff assaulting Marty&amp;#39;s mom, or the occasional mild swears).&lt;/p&gt;\n&lt;/div&gt;", "subreddit": "starterpacks", "name": "t1_dg51h20", "score_hidden": false, "stickied": false, "created": 1491978714.0, "created_utc": 1491949914.0, "depth": 0, "mod_reports": [], "subreddit_type": "public", "ups": 7}}, {"kind": "t1", "data": {"subreddit_id": "t5_34o9s", "removal_reason": null, "link_id": "t3_64u57t", "likes": null, "replies": "", "user_reports": [], "id": "dg7ds55", "gilded": 0, "archived": false, "score": 2, "report_reasons": null, "author": "JavaReallySucks", "parent_id": "t3_64u57t", "subreddit_name_prefixed": "r/starterpacks", "controversiality": 0, "body": "I relate to the early 2000s one more", "edited": false, "downs": 0, "body_html": "&lt;div class=\"md\"&gt;&lt;p&gt;I relate to the early 2000s one more&lt;/p&gt;\n&lt;/div&gt;", "subreddit": "starterpacks", "name": "t1_dg7ds55", "score_hidden": false, "stickied": false, "created": 1492108113.0, "created_utc": 1492079313.0, "depth": 0, "mod_reports": [], "subreddit_type": "public", "ups": 2}}, {"kind": "t1", "data": {"subreddit_id": "t5_34o9s", "removal_reason": null, "link_id": "t3_64u57t", "likes": null, "replies": "", "user_reports": [], "id": "dg75o16", "gilded": 0, "archived": false, "score": 4, "report_reasons": null, "author": "Ruueee", "parent_id": "t3_64u57t", "subreddit_name_prefixed": "r/starterpacks", "controversiality": 0, "body": "Jeez these packs are getting younger and younger,  I was born in 97 and still remember these things as my \"childhood\" I was in fifth grade when Obama was elected ", "edited": false, "downs": 0, "body_html": "&lt;div class=\"md\"&gt;&lt;p&gt;Jeez these packs are getting younger and younger,  I was born in 97 and still remember these things as my &amp;quot;childhood&amp;quot; I was in fifth grade when Obama was elected &lt;/p&gt;\n&lt;/div&gt;", "subreddit": "starterpacks", "name": "t1_dg75o16", "score_hidden": false, "stickied": false, "created": 1492087363.0, "created_utc": 1492058563.0, "depth": 0, "mod_reports": [], "subreddit_type": "public", "ups": 4}}, {"kind": "t1", "data": {"subreddit_id": "t5_34o9s", "removal_reason": null, "link_id": "t3_64u57t", "likes": null, "replies": "", "user_reports": [], "id": "dg5wtut", "gilded": 0, "archived": false, "score": 1, "report_reasons": null, "author": "cegbe", "parent_id": "t3_64u57t", "subreddit_name_prefixed": "r/starterpacks", "controversiality": 0, "body": "Where's call of duty and halo", "edited": false, "downs": 0, "body_html": "&lt;div class=\"md\"&gt;&lt;p&gt;Where&amp;#39;s call of duty and halo&lt;/p&gt;\n&lt;/div&gt;", "subreddit": "starterpacks", "name": "t1_dg5wtut", "score_hidden": false, "stickied": false, "created": 1492035233.0, "created_utc": 1492006433.0, "depth": 0, "mod_reports": [], "subreddit_type": "public", "ups": 1}}, {"kind": "t1", "data": {"subreddit_id": "t5_34o9s", "removal_reason": null, "link_id": "t3_64u57t", "likes": null, "replies": "", "user_reports": [], "id": "dg6z3hc", "gilded": 0, "archived": false, "score": 1, "report_reasons": null, "author": "-xTc-", "parent_id": "t3_64u57t", "subreddit_name_prefixed": "r/starterpacks", "controversiality": 0, "body": "Emphasis on Minecraft!", "edited": false, "downs": 0, "body_html": "&lt;div class=\"md\"&gt;&lt;p&gt;Emphasis on Minecraft!&lt;/p&gt;\n&lt;/div&gt;", "subreddit": "starterpacks", "name": "t1_dg6z3hc", "score_hidden": false, "stickied": false, "created": 1492078126.0, "created_utc": 1492049326.0, "depth": 0, "mod_reports": [], "subreddit_type": "public", "ups": 1}}, {"kind": "t1", "data": {"subreddit_id": "t5_34o9s", "removal_reason": null, "link_id": "t3_64u57t", "likes": null, "replies": "", "user_reports": [], "id": "dg9r5ft", "gilded": 0, "archived": false, "score": 1, "report_reasons": null, "author": "TheGuyDoug", "parent_id": "t3_64u57t", "subreddit_name_prefixed": "r/starterpacks", "controversiality": 0, "body": "Ehh I don't think we're far enough removed from this era in time for it to be anything worth noting about\n\nThe iPhone 6 came out in 2014...\nBarack Obama was our president 3 months ago...\n\nWhat's funny or notable about a list of modern pop culture?", "edited": false, "downs": 0, "body_html": "&lt;div class=\"md\"&gt;&lt;p&gt;Ehh I don&amp;#39;t think we&amp;#39;re far enough removed from this era in time for it to be anything worth noting about&lt;/p&gt;\n\n&lt;p&gt;The iPhone 6 came out in 2014...\nBarack Obama was our president 3 months ago...&lt;/p&gt;\n\n&lt;p&gt;What&amp;#39;s funny or notable about a list of modern pop culture?&lt;/p&gt;\n&lt;/div&gt;", "subreddit": "starterpacks", "name": "t1_dg9r5ft", "score_hidden": false, "stickied": false, "created": 1492232801.0, "created_utc": 1492204001.0, "depth": 0, "mod_reports": [], "subreddit_type": "public", "ups": 1}}, {"kind": "t1", "data": {"subreddit_id": "t5_34o9s", "removal_reason": null, "link_id": "t3_64u57t", "likes": null, "replies": "", "user_reports": [], "id": "dg537ax", "gilded": 0, "archived": false, "score": 0, "report_reasons": null, "author": "pokexchespin", "parent_id": "t3_64u57t", "subreddit_name_prefixed": "r/starterpacks", "controversiality": 0, "body": "Am from 2002, can agree.  We saw ratatouille practically every time there was rain and we stayed in for recess in elementary school that I began to hate it", "edited": false, "downs": 0, "body_html": "&lt;div class=\"md\"&gt;&lt;p&gt;Am from 2002, can agree.  We saw ratatouille practically every time there was rain and we stayed in for recess in elementary school that I began to hate it&lt;/p&gt;\n&lt;/div&gt;", "subreddit": "starterpacks", "name": "t1_dg537ax", "score_hidden": false, "stickied": false, "created": 1491980979.0, "created_utc": 1491952179.0, "depth": 0, "mod_reports": [], "subreddit_type": "public", "ups": 0}}], "after": null, "before": null}}]